{"version":1,"name":"forest","width":104,"height":200,"layers":[{"name":"floor","world":[{"x":0,"y":0,"z":0,"images":["grass"]},{"x":0,"y":4,"z":0,"images":["grass"]},{"x":0,"y":20,"z":0,"images":["grass"]},{"x":0,"y":24,"z":0,"images":["grass"]},{"x":0,"y":28,"z":0,"images":["grass"]},{"x":0,"y":32,"z":0,"images":["grass"]},{"x":0,"y":36,"z":0,"images":["grass"]},{"x":0,"y":40,"z":0,"images":["grass"]},{"x":0,"y":44,"z":0,"images":["grass"]},{"x":0,"y":48,"z":0,"images":["grass"]},{"x":0,"y":52,"z":0,"images":["grass"]},{"x":0,"y":56,"z":0,"images":["grass"]},{"x":0,"y":60,"z":0,"images":["grass"]},{"x":0,"y":64,"z":0,"images":["grass"]},{"x":0,"y":68,"z":0,"images":["grass"]},{"x":0,"y":72,"z":0,"images":["grass"]},{"x":0,"y":76,"z":0,"images":["grass"]},{"x":0,"y":80,"z":0,"images":["grass"]},{"x":0,"y":84,"z":0,"images":["grass"]},{"x":0,"y":88,"z":0,"images":["grass"]},{"x":0,"y":92,"z":0,"images":["grass"]},{"x":0,"y":96,"z":0,"images":["grass"]},{"x":0,"y":100,"z":0,"images":["grass"]},{"x":0,"y":104,"z":0,"images":["grass"]},{"x":0,"y":108,"z":0,"images":["grass"]},{"x":0,"y":112,"z":0,"images":["grass"]},{"x":0,"y":116,"z":0,"images":["grass"]},{"x":0,"y":120,"z":0,"images":["grass"]},{"x":0,"y":124,"z":0,"images":["grass"]},{"x":0,"y":128,"z":0,"images":["grass"]},{"x":0,"y":132,"z":0,"images":["grass"]},{"x":0,"y":136,"z":0,"images":["grass"]},{"x":0,"y":140,"z":0,"images":["grass"]},{"x":0,"y":144,"z":0,"images":["grass"]},{"x":0,"y":148,"z":0,"images":["grass"]},{"x":0,"y":152,"z":0,"images":["grass"]},{"x":0,"y":156,"z":0,"images":["grass"]},{"x":0,"y":160,"z":0,"images":["grass"]},{"x":0,"y":164,"z":0,"images":["grass"]},{"x":0,"y":168,"z":0,"images":["grass"]},{"x":0,"y":172,"z":0,"images":["grass"]},{"x":0,"y":176,"z":0,"images":["grass"]},{"x":0,"y":180,"z":0,"images":["grass"]},{"x":0,"y":184,"z":0,"images":["grass"]},{"x":0,"y":188,"z":0,"images":["grass"]},{"x":0,"y":192,"z":0,"images":["grass"]},{"x":0,"y":196,"z":0,"images":["grass"]},{"x":4,"y":0,"z":0,"images":["grass"]},{"x":4,"y":4,"z":0,"images":["grass"]},{"x":4,"y":8,"z":0,"images":["grass"]},{"x":4,"y":20,"z":0,"images":["grass"]},{"x":4,"y":24,"z":0,"images":["grass"]},{"x":4,"y":28,"z":0,"images":["grass"]},{"x":4,"y":32,"z":0,"images":["grass"]},{"x":4,"y":36,"z":0,"images":["grass"]},{"x":4,"y":40,"z":0,"images":["grass"]},{"x":4,"y":44,"z":0,"images":["grass"]},{"x":4,"y":48,"z":0,"images":["grass"]},{"x":4,"y":52,"z":0,"images":["grass"]},{"x":4,"y":56,"z":0,"images":["grass"]},{"x":4,"y":60,"z":0,"images":["grass"]},{"x":4,"y":64,"z":0,"images":["grass"]},{"x":4,"y":68,"z":0,"images":["grass"]},{"x":4,"y":72,"z":0,"images":["grass"]},{"x":4,"y":76,"z":0,"images":["grass"]},{"x":4,"y":80,"z":0,"images":["grass"]},{"x":4,"y":84,"z":0,"images":["grass"]},{"x":4,"y":88,"z":0,"images":["grass"]},{"x":4,"y":92,"z":0,"images":["grass"]},{"x":4,"y":96,"z":0,"images":["grass"]},{"x":4,"y":100,"z":0,"images":["grass"]},{"x":4,"y":104,"z":0,"images":["grass"]},{"x":4,"y":108,"z":0,"images":["grass"]},{"x":4,"y":112,"z":0,"images":["grass"]},{"x":4,"y":116,"z":0,"images":["grass"]},{"x":4,"y":120,"z":0,"images":["grass"]},{"x":4,"y":124,"z":0,"images":["grass"]},{"x":4,"y":128,"z":0,"images":["grass"]},{"x":4,"y":132,"z":0,"images":["grass"]},{"x":4,"y":136,"z":0,"images":["grass"]},{"x":4,"y":140,"z":0,"images":["grass"]},{"x":4,"y":144,"z":0,"images":["grass"]},{"x":4,"y":148,"z":0,"images":["grass"]},{"x":4,"y":152,"z":0,"images":["grass"]},{"x":4,"y":156,"z":0,"images":["grass"]},{"x":4,"y":160,"z":0,"images":["grass"]},{"x":4,"y":164,"z":0,"images":["grass"]},{"x":4,"y":168,"z":0,"images":["grass"]},{"x":4,"y":172,"z":0,"images":["grass"]},{"x":4,"y":176,"z":0,"images":["grass"]},{"x":4,"y":180,"z":0,"images":["grass"]},{"x":4,"y":184,"z":0,"images":["grass"]},{"x":8,"y":0,"z":0,"images":["grass"]},{"x":8,"y":4,"z":0,"images":["grass"]},{"x":8,"y":8,"z":0,"images":["grass"]},{"x":8,"y":24,"z":0,"images":["grass"]},{"x":8,"y":28,"z":0,"images":["grass"]},{"x":8,"y":32,"z":0,"images":["grass"]},{"x":8,"y":36,"z":0,"images":["grass"]},{"x":8,"y":40,"z":0,"images":["grass"]},{"x":8,"y":44,"z":0,"images":["grass"]},{"x":8,"y":48,"z":0,"images":["grass"]},{"x":8,"y":52,"z":0,"images":["grass"]},{"x":8,"y":56,"z":0,"images":["grass"]},{"x":8,"y":60,"z":0,"images":["grass"]},{"x":8,"y":64,"z":0,"images":["grass"]},{"x":8,"y":68,"z":0,"images":["grass"]},{"x":8,"y":72,"z":0,"images":["grass"]},{"x":8,"y":76,"z":0,"images":["grass"]},{"x":8,"y":80,"z":0,"images":["grass"]},{"x":8,"y":84,"z":0,"images":["grass"]},{"x":8,"y":88,"z":0,"images":["grass"]},{"x":8,"y":92,"z":0,"images":["grass"]},{"x":8,"y":96,"z":0,"images":["grass"]},{"x":8,"y":100,"z":0,"images":["grass"]},{"x":8,"y":104,"z":0,"images":["grass"]},{"x":8,"y":108,"z":0,"images":["grass"]},{"x":8,"y":116,"z":0,"images":["grass"]},{"x":8,"y":132,"z":0,"images":["grass"]},{"x":8,"y":136,"z":0,"images":["grass"]},{"x":8,"y":140,"z":0,"images":["grass"]},{"x":8,"y":144,"z":0,"images":["grass"]},{"x":8,"y":148,"z":0,"images":["grass"]},{"x":8,"y":152,"z":0,"images":["grass"]},{"x":8,"y":156,"z":0,"images":["grass"]},{"x":8,"y":160,"z":0,"images":["grass"]},{"x":8,"y":164,"z":0,"images":["grass"]},{"x":8,"y":168,"z":0,"images":["grass"]},{"x":8,"y":172,"z":0,"images":["grass"]},{"x":8,"y":176,"z":0,"images":["grass"]},{"x":8,"y":180,"z":0,"images":["grass"]},{"x":8,"y":196,"z":0,"images":["grass"]},{"x":12,"y":0,"z":0,"images":["grass"]},{"x":12,"y":4,"z":0,"images":["grass"]},{"x":12,"y":8,"z":0,"images":["grass"]},{"x":12,"y":12,"z":0,"images":["grass"]},{"x":12,"y":16,"z":0,"images":["grass"]},{"x":12,"y":32,"z":0,"images":["grass"]},{"x":12,"y":36,"z":0,"images":["grass"]},{"x":12,"y":40,"z":0,"images":["grass"]},{"x":12,"y":44,"z":0,"images":["grass"]},{"x":12,"y":48,"z":0,"images":["grass"]},{"x":12,"y":52,"z":0,"images":["grass"]},{"x":12,"y":56,"z":0,"images":["grass"]},{"x":12,"y":64,"z":0,"images":["grass"]},{"x":12,"y":68,"z":0,"images":["grass"]},{"x":12,"y":72,"z":0,"images":["grass"]},{"x":12,"y":76,"z":0,"images":["grass"]},{"x":12,"y":80,"z":0,"images":["grass"]},{"x":12,"y":84,"z":0,"images":["grass"]},{"x":12,"y":88,"z":0,"images":["grass"]},{"x":12,"y":92,"z":0,"images":["grass"]},{"x":12,"y":104,"z":0,"images":["grass"]},{"x":12,"y":124,"z":0,"images":["grass"]},{"x":12,"y":136,"z":0,"images":["grass"]},{"x":12,"y":140,"z":0,"images":["grass"]},{"x":12,"y":144,"z":0,"images":["grass"]},{"x":12,"y":148,"z":0,"images":["grass"]},{"x":12,"y":152,"z":0,"images":["grass"]},{"x":12,"y":156,"z":0,"images":["grass"]},{"x":12,"y":160,"z":0,"images":["grass"]},{"x":12,"y":164,"z":0,"images":["grass"]},{"x":12,"y":168,"z":0,"images":["grass"]},{"x":12,"y":172,"z":0,"images":["grass"]},{"x":12,"y":188,"z":0,"images":["grass"]},{"x":12,"y":192,"z":0,"images":["grass"]},{"x":12,"y":196,"z":0,"images":["grass"]},{"x":16,"y":0,"z":0,"images":["grass"]},{"x":16,"y":4,"z":0,"images":["grass"]},{"x":16,"y":8,"z":0,"images":["grass"]},{"x":16,"y":12,"z":0,"images":["grass"]},{"x":16,"y":16,"z":0,"images":["grass"]},{"x":16,"y":20,"z":0,"images":["grass"]},{"x":16,"y":24,"z":0,"images":["grass"]},{"x":16,"y":40,"z":0,"images":["grass"]},{"x":16,"y":44,"z":0,"images":["grass"]},{"x":16,"y":48,"z":0,"images":["grass"]},{"x":16,"y":52,"z":0,"images":["grass"]},{"x":16,"y":72,"z":0,"images":["grass"]},{"x":16,"y":76,"z":0,"images":["grass"]},{"x":16,"y":80,"z":0,"images":["grass"]},{"x":16,"y":84,"z":0,"images":["grass"]},{"x":16,"y":88,"z":0,"images":["grass"]},{"x":16,"y":112,"z":0,"images":["grass"]},{"x":16,"y":116,"z":0,"images":["grass"]},{"x":16,"y":120,"z":0,"images":["grass"]},{"x":16,"y":124,"z":0,"images":["grass"]},{"x":16,"y":128,"z":0,"images":["grass"]},{"x":16,"y":140,"z":0,"images":["grass"]},{"x":16,"y":144,"z":0,"images":["grass"]},{"x":16,"y":148,"z":0,"images":["grass"]},{"x":16,"y":152,"z":0,"images":["grass"]},{"x":16,"y":156,"z":0,"images":["grass"]},{"x":16,"y":180,"z":0,"images":["grass"]},{"x":16,"y":184,"z":0,"images":["grass"]},{"x":16,"y":188,"z":0,"images":["grass"]},{"x":16,"y":192,"z":0,"images":["grass"]},{"x":16,"y":196,"z":0,"images":["grass"]},{"x":20,"y":0,"z":0,"images":["grass"]},{"x":20,"y":4,"z":0,"images":["grass"]},{"x":20,"y":8,"z":0,"images":["grass"]},{"x":20,"y":12,"z":0,"images":["grass"]},{"x":20,"y":16,"z":0,"images":["grass"]},{"x":20,"y":44,"z":0,"images":["grass"]},{"x":20,"y":48,"z":0,"images":["grass"]},{"x":20,"y":52,"z":0,"images":["grass"]},{"x":20,"y":60,"z":0,"images":["grass"]},{"x":20,"y":64,"z":0,"images":["grass"]},{"x":20,"y":108,"z":0,"images":["grass"]},{"x":20,"y":112,"z":0,"images":["grass"]},{"x":20,"y":116,"z":0,"images":["grass"]},{"x":20,"y":120,"z":0,"images":["grass"]},{"x":20,"y":124,"z":0,"images":["grass"]},{"x":20,"y":128,"z":0,"images":["grass"]},{"x":20,"y":132,"z":0,"images":["grass"]},{"x":20,"y":176,"z":0,"images":["grass"]},{"x":20,"y":180,"z":0,"images":["grass"]},{"x":20,"y":184,"z":0,"images":["grass"]},{"x":20,"y":188,"z":0,"images":["grass"]},{"x":20,"y":192,"z":0,"images":["grass"]},{"x":20,"y":196,"z":0,"images":["grass"]},{"x":24,"y":0,"z":0,"images":["grass"]},{"x":24,"y":4,"z":0,"images":["grass"]},{"x":24,"y":8,"z":0,"images":["grass"]},{"x":24,"y":12,"z":0,"images":["grass"]},{"x":24,"y":28,"z":0,"images":["grass"]},{"x":24,"y":32,"z":0,"images":["grass"]},{"x":24,"y":44,"z":0,"images":["grass"]},{"x":24,"y":48,"z":0,"images":["grass"]},{"x":24,"y":60,"z":0,"images":["grass"]},{"x":24,"y":64,"z":0,"images":["grass"]},{"x":24,"y":68,"z":0,"images":["grass"]},{"x":24,"y":72,"z":0,"images":["grass"]},{"x":24,"y":76,"z":0,"images":["grass"]},{"x":24,"y":80,"z":0,"images":["grass"]},{"x":24,"y":84,"z":0,"images":["grass"]},{"x":24,"y":104,"z":0,"images":["grass"]},{"x":24,"y":108,"z":0,"images":["grass"]},{"x":24,"y":112,"z":0,"images":["grass"]},{"x":24,"y":116,"z":0,"images":["grass"]},{"x":24,"y":120,"z":0,"images":["grass"]},{"x":24,"y":124,"z":0,"images":["grass"]},{"x":24,"y":128,"z":0,"images":["grass"]},{"x":24,"y":132,"z":0,"images":["grass"]},{"x":24,"y":136,"z":0,"images":["grass"]},{"x":24,"y":148,"z":0,"images":["grass"]},{"x":24,"y":152,"z":0,"images":["grass"]},{"x":24,"y":156,"z":0,"images":["grass"]},{"x":24,"y":160,"z":0,"images":["grass"]},{"x":24,"y":164,"z":0,"images":["grass"]},{"x":24,"y":168,"z":0,"images":["grass"]},{"x":24,"y":172,"z":0,"images":["grass"]},{"x":24,"y":176,"z":0,"images":["grass"]},{"x":24,"y":180,"z":0,"images":["grass"]},{"x":24,"y":184,"z":0,"images":["grass"]},{"x":24,"y":188,"z":0,"images":["grass"]},{"x":24,"y":192,"z":0,"images":["grass"]},{"x":24,"y":196,"z":0,"images":["grass"]},{"x":28,"y":0,"z":0,"images":["grass"]},{"x":28,"y":4,"z":0,"images":["grass"]},{"x":28,"y":8,"z":0,"images":["grass"]},{"x":28,"y":12,"z":0,"images":["grass"]},{"x":28,"y":24,"z":0,"images":["grass"]},{"x":28,"y":28,"z":0,"images":["grass"]},{"x":28,"y":44,"z":0,"images":["grass"]},{"x":28,"y":48,"z":0,"images":["grass"]},{"x":28,"y":56,"z":0,"images":["grass"]},{"x":28,"y":60,"z":0,"images":["grass"]},{"x":28,"y":64,"z":0,"images":["grass"]},{"x":28,"y":68,"z":0,"images":["grass"]},{"x":28,"y":72,"z":0,"images":["grass"]},{"x":28,"y":76,"z":0,"images":["grass"]},{"x":28,"y":80,"z":0,"images":["grass"]},{"x":28,"y":84,"z":0,"images":["grass"]},{"x":28,"y":88,"z":0,"images":["grass"]},{"x":28,"y":92,"z":0,"images":["grass"]},{"x":28,"y":96,"z":0,"images":["grass"]},{"x":28,"y":100,"z":0,"images":["grass"]},{"x":28,"y":104,"z":0,"images":["grass"]},{"x":28,"y":108,"z":0,"images":["grass"]},{"x":28,"y":112,"z":0,"images":["grass"]},{"x":28,"y":116,"z":0,"images":["grass"]},{"x":28,"y":120,"z":0,"images":["grass"]},{"x":28,"y":136,"z":0,"images":["grass"]},{"x":28,"y":140,"z":0,"images":["grass"]},{"x":28,"y":144,"z":0,"images":["grass"]},{"x":28,"y":148,"z":0,"images":["grass"]},{"x":28,"y":152,"z":0,"images":["grass"]},{"x":28,"y":156,"z":0,"images":["grass"]},{"x":28,"y":160,"z":0,"images":["grass"]},{"x":28,"y":164,"z":0,"images":["grass"]},{"x":28,"y":168,"z":0,"images":["grass"]},{"x":28,"y":172,"z":0,"images":["grass"]},{"x":28,"y":176,"z":0,"images":["grass"]},{"x":28,"y":180,"z":0,"images":["grass"]},{"x":28,"y":184,"z":0,"images":["grass"]},{"x":28,"y":188,"z":0,"images":["grass"]},{"x":28,"y":192,"z":0,"images":["grass"]},{"x":32,"y":0,"z":0,"images":["grass"]},{"x":32,"y":4,"z":0,"images":["grass"]},{"x":32,"y":8,"z":0,"images":["grass"]},{"x":32,"y":12,"z":0,"images":["grass"]},{"x":32,"y":16,"z":0,"images":["grass"]},{"x":32,"y":20,"z":0,"images":["grass"]},{"x":32,"y":24,"z":0,"images":["grass"]},{"x":32,"y":36,"z":0,"images":["grass"]},{"x":32,"y":40,"z":0,"images":["grass"]},{"x":32,"y":44,"z":0,"images":["grass"]},{"x":32,"y":48,"z":0,"images":["grass"]},{"x":32,"y":56,"z":0,"images":["grass"]},{"x":32,"y":60,"z":0,"images":["grass"]},{"x":32,"y":72,"z":0,"images":["grass"]},{"x":32,"y":76,"z":0,"images":["grass"]},{"x":32,"y":80,"z":0,"images":["grass"]},{"x":32,"y":84,"z":0,"images":["grass"]},{"x":32,"y":88,"z":0,"images":["grass"]},{"x":32,"y":92,"z":0,"images":["grass"]},{"x":32,"y":96,"z":0,"images":["grass"]},{"x":32,"y":100,"z":0,"images":["grass"]},{"x":32,"y":104,"z":0,"images":["grass"]},{"x":32,"y":108,"z":0,"images":["grass"]},{"x":32,"y":112,"z":0,"images":["grass"]},{"x":32,"y":116,"z":0,"images":["grass"]},{"x":32,"y":140,"z":0,"images":["grass"]},{"x":32,"y":144,"z":0,"images":["grass"]},{"x":32,"y":148,"z":0,"images":["grass"]},{"x":32,"y":160,"z":0,"images":["grass"]},{"x":32,"y":164,"z":0,"images":["grass"]},{"x":32,"y":168,"z":0,"images":["grass"]},{"x":32,"y":172,"z":0,"images":["grass"]},{"x":32,"y":176,"z":0,"images":["grass"]},{"x":32,"y":180,"z":0,"images":["grass"]},{"x":32,"y":184,"z":0,"images":["grass"]},{"x":32,"y":188,"z":0,"images":["grass"]},{"x":36,"y":0,"z":0,"images":["grass"]},{"x":36,"y":4,"z":0,"images":["grass"]},{"x":36,"y":8,"z":0,"images":["grass"]},{"x":36,"y":12,"z":0,"images":["grass"]},{"x":36,"y":16,"z":0,"images":["grass"]},{"x":36,"y":20,"z":0,"images":["grass"]},{"x":36,"y":32,"z":0,"images":["grass"]},{"x":36,"y":36,"z":0,"images":["grass"]},{"x":36,"y":40,"z":0,"images":["grass"]},{"x":36,"y":44,"z":0,"images":["grass"]},{"x":36,"y":56,"z":0,"images":["grass"]},{"x":36,"y":60,"z":0,"images":["grass"]},{"x":36,"y":64,"z":0,"images":["grass"]},{"x":36,"y":76,"z":0,"images":["grass"]},{"x":36,"y":80,"z":0,"images":["grass"]},{"x":36,"y":84,"z":0,"images":["grass"]},{"x":36,"y":88,"z":0,"images":["grass"]},{"x":36,"y":92,"z":0,"images":["grass"]},{"x":36,"y":96,"z":0,"images":["grass"]},{"x":36,"y":108,"z":0,"images":["grass"]},{"x":36,"y":112,"z":0,"images":["grass"]},{"x":36,"y":164,"z":0,"images":["grass"]},{"x":36,"y":168,"z":0,"images":["grass"]},{"x":36,"y":172,"z":0,"images":["grass"]},{"x":36,"y":176,"z":0,"images":["grass"]},{"x":36,"y":180,"z":0,"images":["grass"]},{"x":36,"y":184,"z":0,"images":["grass"]},{"x":36,"y":196,"z":0,"images":["grass"]},{"x":40,"y":0,"z":0,"images":["grass"]},{"x":40,"y":4,"z":0,"images":["grass"]},{"x":40,"y":8,"z":0,"images":["grass"]},{"x":40,"y":12,"z":0,"images":["grass"]},{"x":40,"y":16,"z":0,"images":["grass"]},{"x":40,"y":20,"z":0,"images":["grass"]},{"x":40,"y":32,"z":0,"images":["grass"]},{"x":40,"y":36,"z":0,"images":["grass"]},{"x":40,"y":44,"z":0,"images":["grass"]},{"x":40,"y":52,"z":0,"images":["grass"]},{"x":40,"y":56,"z":0,"images":["grass"]},{"x":40,"y":60,"z":0,"images":["grass"]},{"x":40,"y":64,"z":0,"images":["grass"]},{"x":40,"y":88,"z":0,"images":["grass"]},{"x":40,"y":136,"z":0,"images":["grass"]},{"x":40,"y":140,"z":0,"images":["grass"]},{"x":40,"y":152,"z":0,"images":["grass"]},{"x":40,"y":156,"z":0,"images":["grass"]},{"x":40,"y":168,"z":0,"images":["grass"]},{"x":40,"y":172,"z":0,"images":["grass"]},{"x":40,"y":176,"z":0,"images":["grass"]},{"x":40,"y":180,"z":0,"images":["grass"]},{"x":40,"y":184,"z":0,"images":["grass"]},{"x":40,"y":192,"z":0,"images":["grass"]},{"x":40,"y":196,"z":0,"images":["grass"]},{"x":44,"y":0,"z":0,"images":["grass"]},{"x":44,"y":4,"z":0,"images":["grass"]},{"x":44,"y":8,"z":0,"images":["grass"]},{"x":44,"y":12,"z":0,"images":["grass"]},{"x":44,"y":32,"z":0,"images":["grass"]},{"x":44,"y":36,"z":0,"images":["grass"]},{"x":44,"y":52,"z":0,"images":["grass"]},{"x":44,"y":56,"z":0,"images":["grass"]},{"x":44,"y":96,"z":0,"images":["grass"]},{"x":44,"y":100,"z":0,"images":["grass"]},{"x":44,"y":104,"z":0,"images":["grass"]},{"x":44,"y":120,"z":0,"images":["grass"]},{"x":44,"y":124,"z":0,"images":["grass"]},{"x":44,"y":132,"z":0,"images":["grass"]},{"x":44,"y":136,"z":0,"images":["grass"]},{"x":44,"y":148,"z":0,"images":["grass"]},{"x":44,"y":152,"z":0,"images":["grass"]},{"x":44,"y":156,"z":0,"images":["grass"]},{"x":44,"y":164,"z":0,"images":["grass"]},{"x":44,"y":168,"z":0,"images":["grass"]},{"x":44,"y":172,"z":0,"images":["grass"]},{"x":44,"y":176,"z":0,"images":["grass"]},{"x":44,"y":180,"z":0,"images":["grass"]},{"x":44,"y":192,"z":0,"images":["grass"]},{"x":44,"y":196,"z":0,"images":["grass"]},{"x":48,"y":0,"z":0,"images":["grass"]},{"x":48,"y":4,"z":0,"images":["grass"]},{"x":48,"y":8,"z":0,"images":["grass"]},{"x":48,"y":32,"z":0,"images":["grass"]},{"x":48,"y":48,"z":0,"images":["grass"]},{"x":48,"y":52,"z":0,"images":["grass"]},{"x":48,"y":56,"z":0,"images":["grass"]},{"x":48,"y":60,"z":0,"images":["grass"]},{"x":48,"y":92,"z":0,"images":["grass"]},{"x":48,"y":96,"z":0,"images":["grass"]},{"x":48,"y":100,"z":0,"images":["grass"]},{"x":48,"y":104,"z":0,"images":["grass"]},{"x":48,"y":108,"z":0,"images":["grass"]},{"x":48,"y":124,"z":0,"images":["grass"]},{"x":48,"y":128,"z":0,"images":["grass"]},{"x":48,"y":132,"z":0,"images":["grass"]},{"x":48,"y":148,"z":0,"images":["grass"]},{"x":48,"y":156,"z":0,"images":["grass"]},{"x":48,"y":172,"z":0,"images":["grass"]},{"x":48,"y":176,"z":0,"images":["grass"]},{"x":48,"y":188,"z":0,"images":["grass"]},{"x":48,"y":192,"z":0,"images":["grass"]},{"x":48,"y":196,"z":0,"images":["grass"]},{"x":52,"y":0,"z":0,"images":["grass"]},{"x":52,"y":4,"z":0,"images":["grass"]},{"x":52,"y":8,"z":0,"images":["grass"]},{"x":52,"y":12,"z":0,"images":["grass"]},{"x":52,"y":24,"z":0,"images":["grass"]},{"x":52,"y":28,"z":0,"images":["grass"]},{"x":52,"y":32,"z":0,"images":["grass"]},{"x":52,"y":52,"z":0,"images":["grass"]},{"x":52,"y":56,"z":0,"images":["grass"]},{"x":52,"y":60,"z":0,"images":["grass"]},{"x":52,"y":64,"z":0,"images":["grass"]},{"x":52,"y":88,"z":0,"images":["grass"]},{"x":52,"y":92,"z":0,"images":["grass"]},{"x":52,"y":96,"z":0,"images":["grass"]},{"x":52,"y":100,"z":0,"images":["grass"]},{"x":52,"y":104,"z":0,"images":["grass"]},{"x":52,"y":108,"z":0,"images":["grass"]},{"x":52,"y":112,"z":0,"images":["grass"]},{"x":52,"y":140,"z":0,"images":["grass"]},{"x":52,"y":144,"z":0,"images":["grass"]},{"x":52,"y":148,"z":0,"images":["grass"]},{"x":52,"y":156,"z":0,"images":["grass"]},{"x":52,"y":184,"z":0,"images":["grass"]},{"x":52,"y":188,"z":0,"images":["grass"]},{"x":52,"y":192,"z":0,"images":["grass"]},{"x":52,"y":196,"z":0,"images":["grass"]},{"x":56,"y":0,"z":0,"images":["grass"]},{"x":56,"y":4,"z":0,"images":["grass"]},{"x":56,"y":8,"z":0,"images":["grass"]},{"x":56,"y":12,"z":0,"images":["grass"]},{"x":56,"y":24,"z":0,"images":["grass"]},{"x":56,"y":28,"z":0,"images":["grass"]},{"x":56,"y":48,"z":0,"images":["grass"]},{"x":56,"y":52,"z":0,"images":["grass"]},{"x":56,"y":84,"z":0,"images":["grass"]},{"x":56,"y":88,"z":0,"images":["grass"]},{"x":56,"y":92,"z":0,"images":["grass"]},{"x":56,"y":96,"z":0,"images":["grass"]},{"x":56,"y":104,"z":0,"images":["grass"]},{"x":56,"y":108,"z":0,"images":["grass"]},{"x":56,"y":112,"z":0,"images":["grass"]},{"x":56,"y":116,"z":0,"images":["grass"]},{"x":56,"y":120,"z":0,"images":["grass"]},{"x":56,"y":124,"z":0,"images":["grass"]},{"x":56,"y":128,"z":0,"images":["grass"]},{"x":56,"y":132,"z":0,"images":["grass"]},{"x":56,"y":136,"z":0,"images":["grass"]},{"x":56,"y":140,"z":0,"images":["grass"]},{"x":56,"y":144,"z":0,"images":["grass"]},{"x":56,"y":156,"z":0,"images":["grass"]},{"x":56,"y":160,"z":0,"images":["grass"]},{"x":56,"y":164,"z":0,"images":["grass"]},{"x":56,"y":168,"z":0,"images":["grass"]},{"x":56,"y":172,"z":0,"images":["grass"]},{"x":56,"y":176,"z":0,"images":["grass"]},{"x":56,"y":180,"z":0,"images":["grass"]},{"x":56,"y":184,"z":0,"images":["grass"]},{"x":56,"y":188,"z":0,"images":["grass"]},{"x":56,"y":192,"z":0,"images":["grass"]},{"x":56,"y":196,"z":0,"images":["grass"]},{"x":60,"y":0,"z":0,"images":["grass"]},{"x":60,"y":4,"z":0,"images":["grass"]},{"x":60,"y":8,"z":0,"images":["grass"]},{"x":60,"y":12,"z":0,"images":["grass"]},{"x":60,"y":16,"z":0,"images":["grass"]},{"x":60,"y":28,"z":0,"images":["grass"]},{"x":60,"y":32,"z":0,"images":["grass"]},{"x":60,"y":52,"z":0,"images":["grass"]},{"x":60,"y":60,"z":0,"images":["grass"]},{"x":60,"y":72,"z":0,"images":["grass"]},{"x":60,"y":76,"z":0,"images":["grass"]},{"x":60,"y":84,"z":0,"images":["grass"]},{"x":60,"y":88,"z":0,"images":["grass"]},{"x":60,"y":92,"z":0,"images":["grass"]},{"x":60,"y":96,"z":0,"images":["grass"]},{"x":60,"y":112,"z":0,"images":["grass"]},{"x":60,"y":116,"z":0,"images":["grass"]},{"x":60,"y":120,"z":0,"images":["grass"]},{"x":60,"y":124,"z":0,"images":["grass"]},{"x":60,"y":128,"z":0,"images":["grass"]},{"x":60,"y":132,"z":0,"images":["grass"]},{"x":60,"y":136,"z":0,"images":["grass"]},{"x":60,"y":164,"z":0,"images":["grass"]},{"x":60,"y":168,"z":0,"images":["grass"]},{"x":60,"y":172,"z":0,"images":["grass"]},{"x":60,"y":176,"z":0,"images":["grass"]},{"x":60,"y":180,"z":0,"images":["grass"]},{"x":60,"y":184,"z":0,"images":["grass"]},{"x":60,"y":188,"z":0,"images":["grass"]},{"x":60,"y":192,"z":0,"images":["grass"]},{"x":60,"y":196,"z":0,"images":["grass"]},{"x":64,"y":0,"z":0,"images":["grass"]},{"x":64,"y":4,"z":0,"images":["grass"]},{"x":64,"y":8,"z":0,"images":["grass"]},{"x":64,"y":12,"z":0,"images":["grass"]},{"x":64,"y":16,"z":0,"images":["grass"]},{"x":64,"y":20,"z":0,"images":["grass"]},{"x":64,"y":36,"z":0,"images":["grass"]},{"x":64,"y":40,"z":0,"images":["grass"]},{"x":64,"y":44,"z":0,"images":["grass"]},{"x":64,"y":48,"z":0,"images":["grass"]},{"x":64,"y":52,"z":0,"images":["grass"]},{"x":64,"y":56,"z":0,"images":["grass"]},{"x":64,"y":60,"z":0,"images":["grass"]},{"x":64,"y":68,"z":0,"images":["grass"]},{"x":64,"y":76,"z":0,"images":["grass"]},{"x":64,"y":88,"z":0,"images":["grass"]},{"x":64,"y":92,"z":0,"images":["grass"]},{"x":64,"y":96,"z":0,"images":["grass"]},{"x":64,"y":100,"z":0,"images":["grass"]},{"x":64,"y":120,"z":0,"images":["grass"]},{"x":64,"y":172,"z":0,"images":["grass"]},{"x":64,"y":176,"z":0,"images":["grass"]},{"x":64,"y":180,"z":0,"images":["grass"]},{"x":64,"y":184,"z":0,"images":["grass"]},{"x":64,"y":188,"z":0,"images":["grass"]},{"x":64,"y":192,"z":0,"images":["grass"]},{"x":64,"y":196,"z":0,"images":["grass"]},{"x":68,"y":0,"z":0,"images":["grass"]},{"x":68,"y":4,"z":0,"images":["grass"]},{"x":68,"y":8,"z":0,"images":["grass"]},{"x":68,"y":12,"z":0,"images":["grass"]},{"x":68,"y":16,"z":0,"images":["grass"]},{"x":68,"y":20,"z":0,"images":["grass"]},{"x":68,"y":24,"z":0,"images":["grass"]},{"x":68,"y":28,"z":0,"images":["grass"]},{"x":68,"y":40,"z":0,"images":["grass"]},{"x":68,"y":44,"z":0,"images":["grass"]},{"x":68,"y":48,"z":0,"images":["grass"]},{"x":68,"y":52,"z":0,"images":["grass"]},{"x":68,"y":64,"z":0,"images":["grass"]},{"x":68,"y":76,"z":0,"images":["grass"]},{"x":68,"y":88,"z":0,"images":["grass"]},{"x":68,"y":92,"z":0,"images":["grass"]},{"x":68,"y":96,"z":0,"images":["grass"]},{"x":68,"y":100,"z":0,"images":["grass"]},{"x":68,"y":104,"z":0,"images":["grass"]},{"x":68,"y":148,"z":0,"images":["grass"]},{"x":68,"y":152,"z":0,"images":["grass"]},{"x":68,"y":156,"z":0,"images":["grass"]},{"x":68,"y":160,"z":0,"images":["grass"]},{"x":68,"y":164,"z":0,"images":["grass"]},{"x":68,"y":168,"z":0,"images":["grass"]},{"x":68,"y":172,"z":0,"images":["grass"]},{"x":68,"y":176,"z":0,"images":["grass"]},{"x":68,"y":180,"z":0,"images":["grass"]},{"x":68,"y":184,"z":0,"images":["grass"]},{"x":68,"y":188,"z":0,"images":["grass"]},{"x":68,"y":192,"z":0,"images":["grass"]},{"x":68,"y":196,"z":0,"images":["grass"]},{"x":72,"y":0,"z":0,"images":["grass"]},{"x":72,"y":12,"z":0,"images":["grass"]},{"x":72,"y":16,"z":0,"images":["grass"]},{"x":72,"y":20,"z":0,"images":["grass"]},{"x":72,"y":24,"z":0,"images":["grass"]},{"x":72,"y":28,"z":0,"images":["grass"]},{"x":72,"y":32,"z":0,"images":["grass"]},{"x":72,"y":48,"z":0,"images":["grass"]},{"x":72,"y":52,"z":0,"images":["grass"]},{"x":72,"y":56,"z":0,"images":["grass"]},{"x":72,"y":72,"z":0,"images":["grass"]},{"x":72,"y":76,"z":0,"images":["grass"]},{"x":72,"y":88,"z":0,"images":["grass"]},{"x":72,"y":92,"z":0,"images":["grass"]},{"x":72,"y":100,"z":0,"images":["grass"]},{"x":72,"y":104,"z":0,"images":["grass"]},{"x":72,"y":108,"z":0,"images":["grass"]},{"x":72,"y":112,"z":0,"images":["grass"]},{"x":72,"y":148,"z":0,"images":["grass"]},{"x":72,"y":152,"z":0,"images":["grass"]},{"x":72,"y":156,"z":0,"images":["grass"]},{"x":72,"y":160,"z":0,"images":["grass"]},{"x":72,"y":164,"z":0,"images":["grass"]},{"x":72,"y":168,"z":0,"images":["grass"]},{"x":72,"y":172,"z":0,"images":["grass"]},{"x":72,"y":176,"z":0,"images":["grass"]},{"x":72,"y":180,"z":0,"images":["grass"]},{"x":72,"y":184,"z":0,"images":["grass"]},{"x":72,"y":188,"z":0,"images":["grass"]},{"x":72,"y":192,"z":0,"images":["grass"]},{"x":72,"y":196,"z":0,"images":["grass"]},{"x":76,"y":0,"z":0,"images":["grass"]},{"x":76,"y":4,"z":0,"images":["grass"]},{"x":76,"y":28,"z":0,"images":["grass"]},{"x":76,"y":32,"z":0,"images":["grass"]},{"x":76,"y":36,"z":0,"images":["grass"]},{"x":76,"y":40,"z":0,"images":["grass"]},{"x":76,"y":56,"z":0,"images":["grass"]},{"x":76,"y":60,"z":0,"images":["grass"]},{"x":76,"y":64,"z":0,"images":["grass"]},{"x":76,"y":68,"z":0,"images":["grass"]},{"x":76,"y":72,"z":0,"images":["grass"]},{"x":76,"y":84,"z":0,"images":["grass"]},{"x":76,"y":88,"z":0,"images":["grass"]},{"x":76,"y":92,"z":0,"images":["grass"]},{"x":76,"y":104,"z":0,"images":["grass"]},{"x":76,"y":108,"z":0,"images":["grass"]},{"x":76,"y":112,"z":0,"images":["grass"]},{"x":76,"y":116,"z":0,"images":["grass"]},{"x":76,"y":120,"z":0,"images":["grass"]},{"x":76,"y":124,"z":0,"images":["grass"]},{"x":76,"y":140,"z":0,"images":["grass"]},{"x":76,"y":144,"z":0,"images":["grass"]},{"x":76,"y":148,"z":0,"images":["grass"]},{"x":76,"y":152,"z":0,"images":["grass"]},{"x":76,"y":156,"z":0,"images":["grass"]},{"x":76,"y":160,"z":0,"images":["grass"]},{"x":76,"y":164,"z":0,"images":["grass"]},{"x":76,"y":168,"z":0,"images":["grass"]},{"x":76,"y":172,"z":0,"images":["grass"]},{"x":76,"y":176,"z":0,"images":["grass"]},{"x":76,"y":180,"z":0,"images":["grass"]},{"x":76,"y":184,"z":0,"images":["grass"]},{"x":76,"y":188,"z":0,"images":["grass"]},{"x":76,"y":192,"z":0,"images":["grass"]},{"x":76,"y":196,"z":0,"images":["grass"]},{"x":80,"y":0,"z":0,"images":["grass"]},{"x":80,"y":4,"z":0,"images":["grass"]},{"x":80,"y":32,"z":0,"images":["grass"]},{"x":80,"y":36,"z":0,"images":["grass"]},{"x":80,"y":40,"z":0,"images":["grass"]},{"x":80,"y":44,"z":0,"images":["grass"]},{"x":80,"y":48,"z":0,"images":["grass"]},{"x":80,"y":80,"z":0,"images":["grass"]},{"x":80,"y":84,"z":0,"images":["grass"]},{"x":80,"y":88,"z":0,"images":["grass"]},{"x":80,"y":92,"z":0,"images":["grass"]},{"x":80,"y":112,"z":0,"images":["grass"]},{"x":80,"y":116,"z":0,"images":["grass"]},{"x":80,"y":120,"z":0,"images":["grass"]},{"x":80,"y":124,"z":0,"images":["grass"]},{"x":80,"y":128,"z":0,"images":["grass"]},{"x":80,"y":132,"z":0,"images":["grass"]},{"x":80,"y":136,"z":0,"images":["grass"]},{"x":80,"y":140,"z":0,"images":["grass"]},{"x":80,"y":144,"z":0,"images":["grass"]},{"x":80,"y":148,"z":0,"images":["grass"]},{"x":80,"y":152,"z":0,"images":["grass"]},{"x":80,"y":156,"z":0,"images":["grass"]},{"x":80,"y":160,"z":0,"images":["grass"]},{"x":80,"y":164,"z":0,"images":["grass"]},{"x":80,"y":168,"z":0,"images":["grass"]},{"x":80,"y":172,"z":0,"images":["grass"]},{"x":80,"y":176,"z":0,"images":["grass"]},{"x":80,"y":180,"z":0,"images":["grass"]},{"x":80,"y":184,"z":0,"images":["grass"]},{"x":80,"y":188,"z":0,"images":["grass"]},{"x":80,"y":192,"z":0,"images":["grass"]},{"x":80,"y":196,"z":0,"images":["grass"]},{"x":84,"y":0,"z":0,"images":["grass"]},{"x":84,"y":4,"z":0,"images":["grass"]},{"x":84,"y":32,"z":0,"images":["grass"]},{"x":84,"y":36,"z":0,"images":["grass"]},{"x":84,"y":40,"z":0,"images":["grass"]},{"x":84,"y":44,"z":0,"images":["grass"]},{"x":84,"y":48,"z":0,"images":["grass"]},{"x":84,"y":52,"z":0,"images":["grass"]},{"x":84,"y":56,"z":0,"images":["grass"]},{"x":84,"y":68,"z":0,"images":["grass"]},{"x":84,"y":72,"z":0,"images":["grass"]},{"x":84,"y":76,"z":0,"images":["grass"]},{"x":84,"y":80,"z":0,"images":["grass"]},{"x":84,"y":128,"z":0,"images":["grass"]},{"x":84,"y":132,"z":0,"images":["grass"]},{"x":84,"y":136,"z":0,"images":["grass"]},{"x":84,"y":140,"z":0,"images":["grass"]},{"x":84,"y":144,"z":0,"images":["grass"]},{"x":84,"y":148,"z":0,"images":["grass"]},{"x":84,"y":152,"z":0,"images":["grass"]},{"x":84,"y":156,"z":0,"images":["grass"]},{"x":84,"y":160,"z":0,"images":["grass"]},{"x":84,"y":164,"z":0,"images":["grass"]},{"x":84,"y":168,"z":0,"images":["grass"]},{"x":84,"y":172,"z":0,"images":["grass"]},{"x":84,"y":176,"z":0,"images":["grass"]},{"x":84,"y":180,"z":0,"images":["grass"]},{"x":84,"y":184,"z":0,"images":["grass"]},{"x":84,"y":188,"z":0,"images":["grass"]},{"x":84,"y":192,"z":0,"images":["grass"]},{"x":84,"y":196,"z":0,"images":["grass"]},{"x":88,"y":0,"z":0,"images":["grass"]},{"x":88,"y":4,"z":0,"images":["grass"]},{"x":88,"y":32,"z":0,"images":["grass"]},{"x":88,"y":36,"z":0,"images":["grass"]},{"x":88,"y":52,"z":0,"images":["grass"]},{"x":88,"y":56,"z":0,"images":["grass"]},{"x":88,"y":60,"z":0,"images":["grass"]},{"x":88,"y":64,"z":0,"images":["grass"]},{"x":88,"y":68,"z":0,"images":["grass"]},{"x":88,"y":72,"z":0,"images":["grass"]},{"x":88,"y":76,"z":0,"images":["grass"]},{"x":88,"y":120,"z":0,"images":["grass"]},{"x":88,"y":140,"z":0,"images":["grass"]},{"x":88,"y":144,"z":0,"images":["grass"]},{"x":88,"y":148,"z":0,"images":["grass"]},{"x":88,"y":152,"z":0,"images":["grass"]},{"x":88,"y":156,"z":0,"images":["grass"]},{"x":88,"y":160,"z":0,"images":["grass"]},{"x":88,"y":164,"z":0,"images":["grass"]},{"x":88,"y":168,"z":0,"images":["grass"]},{"x":88,"y":172,"z":0,"images":["grass"]},{"x":88,"y":176,"z":0,"images":["grass"]},{"x":88,"y":180,"z":0,"images":["grass"]},{"x":88,"y":184,"z":0,"images":["grass"]},{"x":88,"y":188,"z":0,"images":["grass"]},{"x":88,"y":192,"z":0,"images":["grass"]},{"x":88,"y":196,"z":0,"images":["grass"]},{"x":92,"y":0,"z":0,"images":["grass"]},{"x":92,"y":4,"z":0,"images":["grass"]},{"x":92,"y":24,"z":0,"images":["grass"]},{"x":92,"y":28,"z":0,"images":["grass"]},{"x":92,"y":32,"z":0,"images":["grass"]},{"x":92,"y":68,"z":0,"images":["grass"]},{"x":92,"y":72,"z":0,"images":["grass"]},{"x":92,"y":76,"z":0,"images":["grass"]},{"x":92,"y":128,"z":0,"images":["grass"]},{"x":92,"y":132,"z":0,"images":["grass"]},{"x":92,"y":144,"z":0,"images":["grass"]},{"x":92,"y":148,"z":0,"images":["grass"]},{"x":92,"y":152,"z":0,"images":["grass"]},{"x":92,"y":156,"z":0,"images":["grass"]},{"x":92,"y":160,"z":0,"images":["grass"]},{"x":92,"y":164,"z":0,"images":["grass"]},{"x":92,"y":168,"z":0,"images":["grass"]},{"x":92,"y":172,"z":0,"images":["grass"]},{"x":92,"y":176,"z":0,"images":["grass"]},{"x":92,"y":180,"z":0,"images":["grass"]},{"x":92,"y":184,"z":0,"images":["grass"]},{"x":92,"y":188,"z":0,"images":["grass"]},{"x":92,"y":192,"z":0,"images":["grass"]},{"x":92,"y":196,"z":0,"images":["grass"]},{"x":96,"y":0,"z":0,"images":["grass"]},{"x":96,"y":4,"z":0,"images":["grass"]},{"x":96,"y":8,"z":0,"images":["grass"]},{"x":96,"y":12,"z":0,"images":["grass"]},{"x":96,"y":16,"z":0,"images":["grass"]},{"x":96,"y":40,"z":0,"images":["grass"]},{"x":96,"y":44,"z":0,"images":["grass"]},{"x":96,"y":48,"z":0,"images":["grass"]},{"x":96,"y":52,"z":0,"images":["grass"]},{"x":96,"y":84,"z":0,"images":["grass"]},{"x":96,"y":88,"z":0,"images":["grass"]},{"x":96,"y":92,"z":0,"images":["grass"]},{"x":96,"y":96,"z":0,"images":["grass"]},{"x":96,"y":100,"z":0,"images":["grass"]},{"x":96,"y":104,"z":0,"images":["grass"]},{"x":96,"y":108,"z":0,"images":["grass"]},{"x":96,"y":112,"z":0,"images":["grass"]},{"x":96,"y":116,"z":0,"images":["grass"]},{"x":96,"y":120,"z":0,"images":["grass"]},{"x":96,"y":124,"z":0,"images":["grass"]},{"x":96,"y":128,"z":0,"images":["grass"]},{"x":96,"y":132,"z":0,"images":["grass"]},{"x":96,"y":136,"z":0,"images":["grass"]},{"x":96,"y":140,"z":0,"images":["grass"]},{"x":96,"y":144,"z":0,"images":["grass"]},{"x":96,"y":148,"z":0,"images":["grass"]},{"x":96,"y":152,"z":0,"images":["grass"]},{"x":96,"y":156,"z":0,"images":["grass"]},{"x":96,"y":160,"z":0,"images":["grass"]},{"x":96,"y":164,"z":0,"images":["grass"]},{"x":96,"y":168,"z":0,"images":["grass"]},{"x":96,"y":172,"z":0,"images":["grass"]},{"x":96,"y":176,"z":0,"images":["grass"]},{"x":96,"y":180,"z":0,"images":["grass"]},{"x":96,"y":184,"z":0,"images":["grass"]},{"x":96,"y":188,"z":0,"images":["grass"]},{"x":96,"y":192,"z":0,"images":["grass"]},{"x":96,"y":196,"z":0,"images":["grass"]},{"x":100,"y":0,"z":0,"images":["grass"]},{"x":100,"y":4,"z":0,"images":["grass"]},{"x":100,"y":8,"z":0,"images":["grass"]},{"x":100,"y":12,"z":0,"images":["grass"]},{"x":100,"y":16,"z":0,"images":["grass"]},{"x":100,"y":20,"z":0,"images":["grass"]},{"x":100,"y":24,"z":0,"images":["grass"]},{"x":100,"y":28,"z":0,"images":["grass"]},{"x":100,"y":32,"z":0,"images":["grass"]},{"x":100,"y":36,"z":0,"images":["grass"]},{"x":100,"y":40,"z":0,"images":["grass"]},{"x":100,"y":44,"z":0,"images":["grass"]},{"x":100,"y":48,"z":0,"images":["grass"]},{"x":100,"y":52,"z":0,"images":["grass"]},{"x":100,"y":56,"z":0,"images":["grass"]},{"x":100,"y":60,"z":0,"images":["grass"]},{"x":100,"y":64,"z":0,"images":["grass"]},{"x":100,"y":68,"z":0,"images":["grass"]},{"x":100,"y":72,"z":0,"images":["grass"]},{"x":100,"y":76,"z":0,"images":["grass"]},{"x":100,"y":80,"z":0,"images":["grass"]},{"x":100,"y":84,"z":0,"images":["grass"]},{"x":100,"y":88,"z":0,"images":["grass"]},{"x":100,"y":92,"z":0,"images":["grass"]},{"x":100,"y":96,"z":0,"images":["grass"]},{"x":100,"y":100,"z":0,"images":["grass"]},{"x":100,"y":104,"z":0,"images":["grass"]},{"x":100,"y":108,"z":0,"images":["grass"]},{"x":100,"y":112,"z":0,"images":["grass"]},{"x":100,"y":116,"z":0,"images":["grass"]},{"x":100,"y":120,"z":0,"images":["grass"]},{"x":100,"y":124,"z":0,"images":["grass"]},{"x":100,"y":128,"z":0,"images":["grass"]},{"x":100,"y":132,"z":0,"images":["grass"]},{"x":100,"y":136,"z":0,"images":["grass"]},{"x":100,"y":140,"z":0,"images":["grass"]},{"x":100,"y":144,"z":0,"images":["grass"]},{"x":100,"y":148,"z":0,"images":["grass"]},{"x":100,"y":152,"z":0,"images":["grass"]},{"x":100,"y":156,"z":0,"images":["grass"]},{"x":100,"y":160,"z":0,"images":["grass"]},{"x":100,"y":164,"z":0,"images":["grass"]},{"x":100,"y":168,"z":0,"images":["grass"]},{"x":100,"y":172,"z":0,"images":["grass"]},{"x":100,"y":176,"z":0,"images":["grass"]},{"x":100,"y":180,"z":0,"images":["grass"]},{"x":100,"y":184,"z":0,"images":["grass"]},{"x":100,"y":188,"z":0,"images":["grass"]},{"x":100,"y":192,"z":0,"images":["grass"]},{"x":100,"y":196,"z":0,"images":["grass"]},{"x":28,"y":16,"z":0,"images":["grass"]},{"x":24,"y":16,"z":0,"images":["grass"]},{"x":20,"y":20,"z":0,"images":["grass"]},{"x":20,"y":28,"z":0,"images":["grass"]},{"x":20,"y":24,"z":0,"images":["grass"]},{"x":24,"y":24,"z":0,"images":["grass"]},{"x":28,"y":20,"z":0,"images":["grass"]},{"x":24,"y":20,"z":0,"images":["grass"]},{"x":44,"y":72,"z":0,"images":["water"]},{"x":44,"y":80,"z":0,"images":["water"]},{"x":44,"y":76,"z":0,"images":["water"]},{"x":48,"y":72,"z":0,"images":["water"]},{"x":48,"y":76,"z":0,"images":["water"]},{"x":48,"y":80,"z":0,"images":["water"]},{"x":44,"y":84,"z":0,"images":["water"]},{"x":40,"y":84,"z":0,"images":["water"]},{"x":40,"y":80,"z":0,"images":["water"]},{"x":40,"y":76,"z":0,"images":["water"]},{"x":40,"y":72,"z":0,"images":["water"]},{"x":40,"y":68,"z":0,"images":["water"]},{"x":44,"y":68,"z":0,"images":["water"]},{"x":44,"y":60,"z":0,"images":["water"]},{"x":44,"y":64,"z":0,"images":["water"]},{"x":48,"y":64,"z":0,"images":["water"]},{"x":48,"y":68,"z":0,"images":["water"]},{"x":56,"y":76,"z":0,"images":["water"]},{"x":52,"y":84,"z":0,"images":["water"]},{"x":48,"y":84,"z":0,"images":["water"]},{"x":48,"y":88,"z":0,"images":["water"]},{"x":44,"y":88,"z":0,"images":["water"]},{"x":44,"y":92,"z":0,"images":["water"]},{"x":40,"y":92,"z":0,"images":["water"]},{"x":40,"y":96,"z":0,"images":["water"]},{"x":40,"y":100,"z":0,"images":["water"]},{"x":36,"y":100,"z":0,"images":["water"]},{"x":36,"y":104,"z":0,"images":["water"]},{"x":40,"y":104,"z":0,"images":["water"]},{"x":44,"y":108,"z":0,"images":["water"]},{"x":48,"y":112,"z":0,"images":["water"]},{"x":52,"y":116,"z":0,"images":["water"]},{"x":52,"y":120,"z":0,"images":["water"]},{"x":48,"y":116,"z":0,"images":["water"]},{"x":40,"y":108,"z":0,"images":["water"]},{"x":40,"y":112,"z":0,"images":["water"]},{"x":44,"y":112,"z":0,"images":["water"]},{"x":44,"y":116,"z":0,"images":["water"]},{"x":48,"y":120,"z":0,"images":["water"]},{"x":52,"y":124,"z":0,"images":["water"]},{"x":52,"y":128,"z":0,"images":["water"]},{"x":52,"y":132,"z":0,"images":["water"]},{"x":52,"y":136,"z":0,"images":["water"]},{"x":48,"y":136,"z":0,"images":["water"]},{"x":48,"y":140,"z":0,"images":["water"]},{"x":48,"y":144,"z":0,"images":["water"]},{"x":44,"y":140,"z":0,"images":["water"]},{"x":44,"y":144,"z":0,"images":["water"]},{"x":40,"y":144,"z":0,"images":["water"]},{"x":40,"y":148,"z":0,"images":["water"]},{"x":36,"y":148,"z":0,"images":["water"]},{"x":36,"y":152,"z":0,"images":["water"]},{"x":32,"y":152,"z":0,"images":["water"]},{"x":32,"y":156,"z":0,"images":["water"]},{"x":36,"y":156,"z":0,"images":["water"]},{"x":36,"y":160,"z":0,"images":["water"]},{"x":40,"y":164,"z":0,"images":["water"]},{"x":40,"y":160,"z":0,"images":["water"]},{"x":44,"y":160,"z":0,"images":["water"]},{"x":48,"y":160,"z":0,"images":["water"]},{"x":52,"y":160,"z":0,"images":["water"]},{"x":52,"y":164,"z":0,"images":["water"]},{"x":48,"y":164,"z":0,"images":["water"]},{"x":48,"y":168,"z":0,"images":["water"]},{"x":52,"y":168,"z":0,"images":["water"]},{"x":52,"y":172,"z":0,"images":["water"]},{"x":52,"y":176,"z":0,"images":["water"]},{"x":52,"y":180,"z":0,"images":["water"]},{"x":48,"y":180,"z":0,"images":["water"]},{"x":48,"y":184,"z":0,"images":["water"]},{"x":44,"y":184,"z":0,"images":["water"]},{"x":44,"y":188,"z":0,"images":["water"]},{"x":40,"y":188,"z":0,"images":["water"]},{"x":36,"y":188,"z":0,"images":["water"]},{"x":36,"y":192,"z":0,"images":["water"]},{"x":32,"y":192,"z":0,"images":["water"]},{"x":32,"y":196,"z":0,"images":["water"]},{"x":28,"y":196,"z":0,"images":["water"]},{"x":36,"y":144,"z":0,"images":["water"]},{"x":36,"y":140,"z":0,"images":["water"]},{"x":36,"y":136,"z":0,"images":["water"]},{"x":32,"y":136,"z":0,"images":["water"]},{"x":32,"y":132,"z":0,"images":["water"]},{"x":36,"y":132,"z":0,"images":["water"]},{"x":40,"y":116,"z":0,"images":["water"]},{"x":36,"y":116,"z":0,"images":["water"]},{"x":32,"y":128,"z":0,"images":["water"]},{"x":28,"y":124,"z":0,"images":["water"]},{"x":28,"y":128,"z":0,"images":["water"]},{"x":28,"y":132,"z":0,"images":["water"]},{"x":36,"y":72,"z":0,"images":["water"]},{"x":36,"y":68,"z":0,"images":["water"]},{"x":32,"y":68,"z":0,"images":["water"]},{"x":32,"y":64,"z":0,"images":["water"]},{"x":52,"y":68,"z":0,"images":["water"]},{"x":56,"y":64,"z":0,"images":["water"]},{"x":56,"y":60,"z":0,"images":["water"]},{"x":60,"y":56,"z":0,"images":["water"]},{"x":56,"y":56,"z":0,"images":["water"]},{"x":52,"y":72,"z":0,"images":["water"]},{"x":56,"y":72,"z":0,"images":["water"]},{"x":56,"y":68,"z":0,"images":["water"]},{"x":60,"y":68,"z":0,"images":["water"]},{"x":64,"y":64,"z":0,"images":["water"]},{"x":52,"y":76,"z":0,"images":["water"]},{"x":52,"y":80,"z":0,"images":["water"]},{"x":56,"y":80,"z":0,"images":["water"]},{"x":60,"y":80,"z":0,"images":["water"]},{"x":64,"y":80,"z":0,"images":["water"]},{"x":64,"y":84,"z":0,"images":["water"]},{"x":68,"y":84,"z":0,"images":["water"]},{"x":72,"y":84,"z":0,"images":["water"]},{"x":68,"y":80,"z":0,"images":["water"]},{"x":72,"y":80,"z":0,"images":["water"]},{"x":76,"y":80,"z":0,"images":["water"]},{"x":76,"y":76,"z":0,"images":["water"]},{"x":80,"y":76,"z":0,"images":["water"]},{"x":80,"y":72,"z":0,"images":["water"]},{"x":80,"y":68,"z":0,"images":["water"]},{"x":80,"y":64,"z":0,"images":["water"]},{"x":84,"y":64,"z":0,"images":["water"]},{"x":84,"y":60,"z":0,"images":["water"]},{"x":80,"y":60,"z":0,"images":["water"]},{"x":80,"y":56,"z":0,"images":["water"]},{"x":80,"y":52,"z":0,"images":["water"]},{"x":76,"y":52,"z":0,"images":["water"]},{"x":76,"y":48,"z":0,"images":["water"]},{"x":76,"y":44,"z":0,"images":["water"]},{"x":72,"y":44,"z":0,"images":["water"]},{"x":72,"y":40,"z":0,"images":["water"]},{"x":72,"y":36,"z":0,"images":["water"]},{"x":68,"y":36,"z":0,"images":["water"]},{"x":68,"y":32,"z":0,"images":["water"]},{"x":64,"y":32,"z":0,"images":["water"]},{"x":64,"y":28,"z":0,"images":["water"]},{"x":48,"y":28,"z":0,"images":["water"]},{"x":44,"y":28,"z":0,"images":["water"]},{"x":48,"y":24,"z":0,"images":["water"]},{"x":48,"y":20,"z":0,"images":["water"]},{"x":52,"y":20,"z":0,"images":["water"]},{"x":56,"y":20,"z":0,"images":["water"]},{"x":64,"y":24,"z":0,"images":["water"]},{"x":60,"y":24,"z":0,"images":["water"]},{"x":60,"y":20,"z":0,"images":["water"]},{"x":56,"y":16,"z":0,"images":["water"]},{"x":52,"y":16,"z":0,"images":["water"]},{"x":48,"y":12,"z":0,"images":["water"]},{"x":48,"y":16,"z":0,"images":["water"]},{"x":44,"y":16,"z":0,"images":["water"]},{"x":44,"y":20,"z":0,"images":["water"]},{"x":44,"y":24,"z":0,"images":["water"]},{"x":40,"y":24,"z":0,"images":["water"]},{"x":40,"y":28,"z":0,"images":["water"]},{"x":36,"y":24,"z":0,"images":["water"]},{"x":36,"y":28,"z":0,"images":["water"]},{"x":32,"y":28,"z":0,"images":["water"]},{"x":32,"y":32,"z":0,"images":["water"]},{"x":28,"y":32,"z":0,"images":["water"]},{"x":28,"y":36,"z":0,"images":["water"]},{"x":20,"y":32,"z":0,"images":["water"]},{"x":16,"y":32,"z":0,"images":["water"]},{"x":16,"y":28,"z":0,"images":["water"]},{"x":12,"y":28,"z":0,"images":["water"]},{"x":12,"y":24,"z":0,"images":["water"]},{"x":12,"y":20,"z":0,"images":["water"]},{"x":8,"y":20,"z":0,"images":["water"]},{"x":8,"y":16,"z":0,"images":["water"]},{"x":8,"y":12,"z":0,"images":["water"]},{"x":4,"y":12,"z":0,"images":["water"]},{"x":0,"y":8,"z":0,"images":["water"]},{"x":0,"y":16,"z":0,"images":["water"]},{"x":0,"y":12,"z":0,"images":["water"]},{"x":4,"y":16,"z":0,"images":["water"]},{"x":16,"y":36,"z":0,"images":["water"]},{"x":20,"y":40,"z":0,"images":["water"]},{"x":20,"y":36,"z":0,"images":["water"]},{"x":24,"y":36,"z":0,"images":["water"]},{"x":24,"y":40,"z":0,"images":["water"]},{"x":28,"y":40,"z":0,"images":["water"]},{"x":44,"y":128,"z":0,"images":["sand"]},{"x":40,"y":132,"z":0,"images":["sand"]},{"x":40,"y":128,"z":0,"images":["sand"]},{"x":40,"y":120,"z":0,"images":["grass"]},{"x":40,"y":124,"z":0,"images":["grass"]},{"x":36,"y":120,"z":0,"images":["water"]},{"x":32,"y":120,"z":0,"images":["water"]},{"x":32,"y":124,"z":0,"images":["water"]},{"x":36,"y":124,"z":0,"images":["water"]},{"x":36,"y":128,"z":0,"images":["water"]},{"x":56,"y":148,"z":0,"images":["sand"]},{"x":60,"y":140,"z":0,"images":["sand"]},{"x":64,"y":128,"z":0,"images":["sand"]},{"x":64,"y":124,"z":0,"images":["sand"]},{"x":68,"y":128,"z":0,"images":["sand"]},{"x":64,"y":132,"z":0,"images":["sand"]},{"x":64,"y":136,"z":0,"images":["sand"]},{"x":68,"y":140,"z":0,"images":["sand"]},{"x":64,"y":140,"z":0,"images":["sand"]},{"x":60,"y":148,"z":0,"images":["sand"]},{"x":68,"y":144,"z":0,"images":["sand"]},{"x":72,"y":144,"z":0,"images":["sand"]},{"x":72,"y":140,"z":0,"images":["sand"]},{"x":76,"y":136,"z":0,"images":["sand"]},{"x":76,"y":128,"z":0,"images":["sand"]},{"x":76,"y":132,"z":0,"images":["sand"]},{"x":72,"y":136,"z":0,"images":["sand"]},{"x":68,"y":136,"z":0,"images":["sand"]},{"x":68,"y":132,"z":0,"images":["sand"]},{"x":72,"y":132,"z":0,"images":["sand"]},{"x":72,"y":128,"z":0,"images":["sand"]},{"x":72,"y":124,"z":0,"images":["sand"]},{"x":72,"y":120,"z":0,"images":["sand"]},{"x":72,"y":116,"z":0,"images":["sand"]},{"x":68,"y":112,"z":0,"images":["sand"]},{"x":68,"y":108,"z":0,"images":["sand"]},{"x":64,"y":104,"z":0,"images":["sand"]},{"x":56,"y":100,"z":0,"images":["sand"]},{"x":60,"y":100,"z":0,"images":["sand"]},{"x":60,"y":104,"z":0,"images":["sand"]},{"x":60,"y":108,"z":0,"images":["sand"]},{"x":64,"y":108,"z":0,"images":["sand"]},{"x":64,"y":112,"z":0,"images":["sand"]},{"x":64,"y":116,"z":0,"images":["sand"]},{"x":68,"y":116,"z":0,"images":["sand"]},{"x":68,"y":120,"z":0,"images":["sand"]},{"x":68,"y":124,"z":0,"images":["sand"]},{"x":60,"y":144,"z":0,"images":["sand"]},{"x":64,"y":144,"z":0,"images":["sand"]},{"x":64,"y":148,"z":0,"images":["sand"]},{"x":64,"y":152,"z":0,"images":["sand"]},{"x":64,"y":156,"z":0,"images":["sand"]},{"x":64,"y":168,"z":0,"images":["sand"]},{"x":64,"y":164,"z":0,"images":["sand"]},{"x":64,"y":160,"z":0,"images":["sand"]},{"x":60,"y":160,"z":0,"images":["sand"]},{"x":60,"y":156,"z":0,"images":["sand"]},{"x":60,"y":152,"z":0,"images":["sand"]},{"x":56,"y":152,"z":0,"images":["sand"]},{"x":52,"y":152,"z":0,"images":["sand"]},{"x":48,"y":152,"z":0,"images":["sand"]},{"x":8,"y":192,"z":0,"images":["mud"]},{"x":8,"y":188,"z":0,"images":["mud"]},{"x":8,"y":184,"z":0,"images":["mud"]},{"x":12,"y":184,"z":0,"images":["mud"]},{"x":12,"y":180,"z":0,"images":["mud"]},{"x":20,"y":172,"z":0,"images":["mud"]},{"x":20,"y":164,"z":0,"images":["mud"]},{"x":20,"y":168,"z":0,"images":["mud"]},{"x":16,"y":168,"z":0,"images":["mud"]},{"x":16,"y":172,"z":0,"images":["mud"]},{"x":16,"y":176,"z":0,"images":["mud"]},{"x":12,"y":176,"z":0,"images":["mud"]},{"x":16,"y":164,"z":0,"images":["mud"]},{"x":16,"y":160,"z":0,"images":["mud"]},{"x":20,"y":160,"z":0,"images":["mud"]},{"x":20,"y":156,"z":0,"images":["mud"]},{"x":20,"y":152,"z":0,"images":["mud"]},{"x":20,"y":148,"z":0,"images":["mud"]},{"x":20,"y":144,"z":0,"images":["mud"]},{"x":24,"y":144,"z":0,"images":["mud"]},{"x":24,"y":140,"z":0,"images":["mud"]},{"x":16,"y":132,"z":0,"images":["mud"]},{"x":16,"y":136,"z":0,"images":["mud"]},{"x":20,"y":136,"z":0,"images":["mud"]},{"x":20,"y":140,"z":0,"images":["mud"]},{"x":12,"y":120,"z":0,"images":["mud"]},{"x":12,"y":116,"z":0,"images":["mud"]},{"x":8,"y":120,"z":0,"images":["mud"]},{"x":8,"y":124,"z":0,"images":["mud"]},{"x":8,"y":128,"z":0,"images":["mud"]},{"x":12,"y":132,"z":0,"images":["mud"]},{"x":12,"y":128,"z":0,"images":["mud"]},{"x":8,"y":112,"z":0,"images":["mud"]},{"x":12,"y":112,"z":0,"images":["mud"]},{"x":12,"y":108,"z":0,"images":["mud"]},{"x":16,"y":108,"z":0,"images":["mud"]},{"x":16,"y":104,"z":0,"images":["mud"]},{"x":20,"y":104,"z":0,"images":["mud"]},{"x":24,"y":100,"z":0,"images":["mud"]},{"x":24,"y":96,"z":0,"images":["mud"]},{"x":16,"y":92,"z":0,"images":["mud"]},{"x":16,"y":96,"z":0,"images":["mud"]},{"x":12,"y":96,"z":0,"images":["mud"]},{"x":12,"y":100,"z":0,"images":["mud"]},{"x":16,"y":100,"z":0,"images":["mud"]},{"x":20,"y":100,"z":0,"images":["mud"]},{"x":20,"y":96,"z":0,"images":["mud"]},{"x":20,"y":92,"z":0,"images":["mud"]},{"x":24,"y":92,"z":0,"images":["mud"]},{"x":24,"y":88,"z":0,"images":["mud"]},{"x":16,"y":68,"z":0,"images":["mud"]},{"x":16,"y":64,"z":0,"images":["mud"]},{"x":20,"y":68,"z":0,"images":["mud"]},{"x":20,"y":72,"z":0,"images":["mud"]},{"x":20,"y":76,"z":0,"images":["mud"]},{"x":20,"y":80,"z":0,"images":["mud"]},{"x":20,"y":88,"z":0,"images":["mud"]},{"x":20,"y":84,"z":0,"images":["mud"]},{"x":12,"y":60,"z":0,"images":["mud"]},{"x":16,"y":60,"z":0,"images":["mud"]},{"x":16,"y":56,"z":0,"images":["mud"]},{"x":20,"y":56,"z":0,"images":["mud"]},{"x":24,"y":56,"z":0,"images":["mud"]},{"x":44,"y":44,"z":0,"images":["mud"]},{"x":44,"y":48,"z":0,"images":["mud"]},{"x":40,"y":48,"z":0,"images":["mud"]},{"x":36,"y":48,"z":0,"images":["mud"]},{"x":36,"y":52,"z":0,"images":["mud"]},{"x":32,"y":52,"z":0,"images":["mud"]},{"x":28,"y":52,"z":0,"images":["mud"]},{"x":24,"y":52,"z":0,"images":["mud"]},{"x":40,"y":40,"z":0,"images":["mud"]},{"x":44,"y":40,"z":0,"images":["mud"]},{"x":52,"y":40,"z":0,"images":["mud"]},{"x":56,"y":40,"z":0,"images":["mud"]},{"x":60,"y":40,"z":0,"images":["mud"]},{"x":60,"y":36,"z":0,"images":["mud"]},{"x":56,"y":32,"z":0,"images":["mud"]},{"x":56,"y":36,"z":0,"images":["mud"]},{"x":52,"y":36,"z":0,"images":["mud"]},{"x":48,"y":36,"z":0,"images":["mud"]},{"x":48,"y":40,"z":0,"images":["mud"]},{"x":48,"y":44,"z":0,"images":["mud"]},{"x":52,"y":48,"z":0,"images":["mud"]},{"x":52,"y":44,"z":0,"images":["mud"]},{"x":56,"y":44,"z":0,"images":["mud"]},{"x":60,"y":44,"z":0,"images":["mud"]},{"x":60,"y":48,"z":0,"images":["mud"]},{"x":68,"y":56,"z":0,"images":["mud"]},{"x":68,"y":60,"z":0,"images":["mud"]},{"x":72,"y":60,"z":0,"images":["mud"]},{"x":72,"y":64,"z":0,"images":["mud"]},{"x":68,"y":68,"z":0,"images":["mud"]},{"x":72,"y":68,"z":0,"images":["mud"]},{"x":64,"y":72,"z":0,"images":["mud"]},{"x":68,"y":72,"z":0,"images":["mud"]},{"x":60,"y":64,"z":0,"images":["water"]},{"x":4,"y":188,"z":0,"images":["mud"]},{"x":4,"y":192,"z":0,"images":["mud"]},{"x":4,"y":196,"z":0,"images":["mud"]},{"x":76,"y":12,"z":0,"images":["moss"]},{"x":80,"y":12,"z":0,"images":["moss"]},{"x":84,"y":16,"z":0,"images":["moss"]},{"x":84,"y":24,"z":0,"images":["moss"]},{"x":84,"y":20,"z":0,"images":["moss"]},{"x":80,"y":20,"z":0,"images":["moss"]},{"x":80,"y":16,"z":0,"images":["moss"]},{"x":76,"y":16,"z":0,"images":["moss"]},{"x":76,"y":20,"z":0,"images":["moss"]},{"x":76,"y":24,"z":0,"images":["moss"]},{"x":80,"y":24,"z":0,"images":["moss"]},{"x":80,"y":28,"z":0,"images":["moss"]},{"x":84,"y":28,"z":0,"images":["moss"]},{"x":88,"y":28,"z":0,"images":["moss"]},{"x":88,"y":24,"z":0,"images":["moss"]},{"x":88,"y":20,"z":0,"images":["moss"]},{"x":92,"y":12,"z":0,"images":["moss"]},{"x":92,"y":8,"z":0,"images":["moss"]},{"x":88,"y":8,"z":0,"images":["moss"]},{"x":72,"y":4,"z":0,"images":["moss"]},{"x":72,"y":8,"z":0,"images":["moss"]},{"x":76,"y":8,"z":0,"images":["moss"]},{"x":80,"y":8,"z":0,"images":["moss"]},{"x":84,"y":8,"z":0,"images":["moss"]},{"x":84,"y":12,"z":0,"images":["moss"]},{"x":88,"y":12,"z":0,"images":["moss"]},{"x":88,"y":16,"z":0,"images":["moss"]},{"x":92,"y":16,"z":0,"images":["moss"]},{"x":92,"y":20,"z":0,"images":["moss"]},{"x":96,"y":20,"z":0,"images":["moss"]},{"x":96,"y":24,"z":0,"images":["moss"]},{"x":96,"y":28,"z":0,"images":["moss"]},{"x":96,"y":32,"z":0,"images":["moss"]},{"x":96,"y":36,"z":0,"images":["moss"]},{"x":92,"y":36,"z":0,"images":["moss"]},{"x":92,"y":40,"z":0,"images":["moss"]},{"x":92,"y":44,"z":0,"images":["moss"]},{"x":88,"y":40,"z":0,"images":["moss"]},{"x":88,"y":44,"z":0,"images":["moss"]},{"x":88,"y":48,"z":0,"images":["moss"]},{"x":92,"y":48,"z":0,"images":["moss"]},{"x":92,"y":52,"z":0,"images":["moss"]},{"x":92,"y":56,"z":0,"images":["moss"]},{"x":96,"y":56,"z":0,"images":["moss"]},{"x":96,"y":60,"z":0,"images":["moss"]},{"x":92,"y":60,"z":0,"images":["moss"]},{"x":92,"y":64,"z":0,"images":["moss"]},{"x":96,"y":64,"z":0,"images":["moss"]},{"x":96,"y":68,"z":0,"images":["moss"]},{"x":96,"y":72,"z":0,"images":["moss"]},{"x":96,"y":76,"z":0,"images":["moss"]},{"x":96,"y":80,"z":0,"images":["moss"]},{"x":92,"y":80,"z":0,"images":["moss"]},{"x":88,"y":80,"z":0,"images":["moss"]},{"x":84,"y":84,"z":0,"images":["moss"]},{"x":84,"y":88,"z":0,"images":["moss"]},{"x":84,"y":96,"z":0,"images":["moss"]},{"x":84,"y":92,"z":0,"images":["moss"]},{"x":88,"y":84,"z":0,"images":["moss"]},{"x":88,"y":88,"z":0,"images":["moss"]},{"x":88,"y":96,"z":0,"images":["moss"]},{"x":88,"y":92,"z":0,"images":["moss"]},{"x":92,"y":84,"z":0,"images":["moss"]},{"x":92,"y":88,"z":0,"images":["moss"]},{"x":92,"y":92,"z":0,"images":["moss"]},{"x":92,"y":96,"z":0,"images":["moss"]},{"x":92,"y":100,"z":0,"images":["moss"]},{"x":92,"y":104,"z":0,"images":["moss"]},{"x":88,"y":100,"z":0,"images":["moss"]},{"x":84,"y":100,"z":0,"images":["moss"]},{"x":88,"y":104,"z":0,"images":["moss"]},{"x":84,"y":108,"z":0,"images":["moss"]},{"x":84,"y":104,"z":0,"images":["moss"]},{"x":76,"y":100,"z":0,"images":["moss"]},{"x":72,"y":96,"z":0,"images":["moss"]},{"x":76,"y":96,"z":0,"images":["moss"]},{"x":80,"y":96,"z":0,"images":["moss"]},{"x":80,"y":100,"z":0,"images":["moss"]},{"x":80,"y":104,"z":0,"images":["moss"]},{"x":80,"y":108,"z":0,"images":["moss"]},{"x":88,"y":116,"z":0,"images":["moss"]},{"x":92,"y":124,"z":0,"images":["moss"]},{"x":92,"y":120,"z":0,"images":["moss"]},{"x":92,"y":116,"z":0,"images":["moss"]},{"x":92,"y":112,"z":0,"images":["moss"]},{"x":92,"y":108,"z":0,"images":["moss"]},{"x":88,"y":108,"z":0,"images":["moss"]},{"x":88,"y":112,"z":0,"images":["moss"]},{"x":84,"y":112,"z":0,"images":["moss"]},{"x":84,"y":116,"z":0,"images":["moss"]},{"x":84,"y":120,"z":0,"images":["moss"]},{"x":84,"y":124,"z":0,"images":["moss"]},{"x":88,"y":124,"z":0,"images":["moss"]},{"x":88,"y":128,"z":0,"images":["moss"]},{"x":88,"y":132,"z":0,"images":["moss"]},{"x":88,"y":136,"z":0,"images":["moss"]},{"x":92,"y":136,"z":0,"images":["moss"]},{"x":92,"y":140,"z":0,"images":["moss"]}]},{"name":"edge","world":[{"x":23,"y":17,"z":0,"images":["grass.edge1.n"]},{"x":25,"y":19,"z":0,"images":["grass.edge1.e"]},{"x":21,"y":19,"z":0,"images":["grass.edge1.w"]},{"x":19,"y":21,"z":0,"images":["grass.edge2.n"]},{"x":17,"y":23,"z":0,"images":["grass.edge2.w"]},{"x":19,"y":25,"z":0,"images":["grass.edge2.n"]},{"x":21,"y":27,"z":0,"images":["grass.edge2.e"]},{"x":23,"y":21,"z":0,"images":["grass.edge2.n"]},{"x":23,"y":25,"z":0,"images":["grass.edge2.s"]},{"x":25,"y":23,"z":0,"images":["grass.edge2.e"]},{"x":21,"y":23,"z":0,"images":["grass.edge2.w"]},{"x":37,"y":79,"z":0,"images":["grass.edge3.w"]},{"x":43,"y":57,"z":0,"images":["grass.edge3.n"]},{"x":45,"y":59,"z":0,"images":["grass.edge3.e"]},{"x":41,"y":59,"z":0,"images":["grass.edge3.w"]},{"x":41,"y":63,"z":0,"images":["grass.edge3.w"]},{"x":39,"y":85,"z":0,"images":["grass.edge3.s"]},{"x":37,"y":83,"z":0,"images":["grass.edge3.w"]},{"x":47,"y":89,"z":0,"images":["grass.edge3.s"]},{"x":49,"y":87,"z":0,"images":["grass.edge3.e"]},{"x":41,"y":87,"z":0,"images":["grass.edge3.w"]},{"x":39,"y":89,"z":0,"images":["grass.edge3.n"]},{"x":37,"y":91,"z":0,"images":["grass.edge3.w"]},{"x":43,"y":93,"z":0,"images":["grass.edge3.s"]},{"x":45,"y":91,"z":0,"images":["grass.edge3.e"]},{"x":41,"y":95,"z":0,"images":["grass.edge3.e"]},{"x":37,"y":95,"z":0,"images":["grass.edge3.w"]},{"x":35,"y":97,"z":0,"images":["grass.edge3.n"]},{"x":33,"y":99,"z":0,"images":["grass.edge3.w"]},{"x":41,"y":99,"z":0,"images":["grass.edge3.e"]},{"x":35,"y":105,"z":0,"images":["grass.edge3.s"]},{"x":33,"y":103,"z":0,"images":["grass.edge3.w"]},{"x":41,"y":103,"z":0,"images":["grass.edge3.e"]},{"x":37,"y":107,"z":0,"images":["grass.edge3.w"]},{"x":43,"y":105,"z":0,"images":["grass.edge3.n"]},{"x":45,"y":107,"z":0,"images":["grass.edge3.e"]},{"x":47,"y":109,"z":0,"images":["grass.edge3.n"]},{"x":49,"y":111,"z":0,"images":["grass.edge3.e"]},{"x":51,"y":113,"z":0,"images":["grass.edge3.n"]},{"x":53,"y":115,"z":0,"images":["grass.edge3.e"]},{"x":47,"y":121,"z":0,"images":["grass.edge3.s"]},{"x":45,"y":119,"z":0,"images":["grass.edge3.w"]},{"x":53,"y":119,"z":0,"images":["grass.edge3.e"]},{"x":53,"y":123,"z":0,"images":["grass.edge3.e"]},{"x":49,"y":123,"z":0,"images":["grass.edge3.w"]},{"x":53,"y":127,"z":0,"images":["grass.edge3.e"]},{"x":49,"y":127,"z":0,"images":["grass.edge3.w"]},{"x":53,"y":131,"z":0,"images":["grass.edge3.e"]},{"x":49,"y":131,"z":0,"images":["grass.edge3.w"]},{"x":51,"y":137,"z":0,"images":["grass.edge3.s"]},{"x":53,"y":135,"z":0,"images":["grass.edge3.e"]},{"x":47,"y":133,"z":0,"images":["grass.edge3.n"]},{"x":45,"y":135,"z":0,"images":["grass.edge3.w"]},{"x":49,"y":139,"z":0,"images":["grass.edge3.e"]},{"x":47,"y":145,"z":0,"images":["grass.edge3.s"]},{"x":49,"y":143,"z":0,"images":["grass.edge3.e"]},{"x":43,"y":137,"z":0,"images":["grass.edge3.n"]},{"x":41,"y":139,"z":0,"images":["grass.edge3.w"]},{"x":43,"y":145,"z":0,"images":["grass.edge3.s"]},{"x":31,"y":149,"z":0,"images":["grass.edge3.n"]},{"x":29,"y":151,"z":0,"images":["grass.edge3.w"]},{"x":37,"y":151,"z":0,"images":["grass.edge3.e"]},{"x":31,"y":157,"z":0,"images":["grass.edge3.s"]},{"x":29,"y":155,"z":0,"images":["grass.edge3.w"]},{"x":37,"y":155,"z":0,"images":["grass.edge3.e"]},{"x":35,"y":161,"z":0,"images":["grass.edge3.s"]},{"x":33,"y":159,"z":0,"images":["grass.edge3.w"]},{"x":39,"y":157,"z":0,"images":["grass.edge3.n"]},{"x":39,"y":165,"z":0,"images":["grass.edge3.s"]},{"x":41,"y":163,"z":0,"images":["grass.edge3.e"]},{"x":37,"y":163,"z":0,"images":["grass.edge3.w"]},{"x":43,"y":157,"z":0,"images":["grass.edge3.n"]},{"x":43,"y":161,"z":0,"images":["grass.edge3.s"]},{"x":47,"y":157,"z":0,"images":["grass.edge3.n"]},{"x":51,"y":157,"z":0,"images":["grass.edge3.n"]},{"x":53,"y":159,"z":0,"images":["grass.edge3.e"]},{"x":45,"y":163,"z":0,"images":["grass.edge3.w"]},{"x":53,"y":163,"z":0,"images":["grass.edge3.e"]},{"x":47,"y":169,"z":0,"images":["grass.edge3.s"]},{"x":45,"y":167,"z":0,"images":["grass.edge3.w"]},{"x":53,"y":167,"z":0,"images":["grass.edge3.e"]},{"x":53,"y":171,"z":0,"images":["grass.edge3.e"]},{"x":49,"y":171,"z":0,"images":["grass.edge3.w"]},{"x":53,"y":175,"z":0,"images":["grass.edge3.e"]},{"x":49,"y":175,"z":0,"images":["grass.edge3.w"]},{"x":51,"y":181,"z":0,"images":["grass.edge3.s"]},{"x":53,"y":179,"z":0,"images":["grass.edge3.e"]},{"x":47,"y":177,"z":0,"images":["grass.edge3.n"]},{"x":45,"y":179,"z":0,"images":["grass.edge3.w"]},{"x":47,"y":185,"z":0,"images":["grass.edge3.s"]},{"x":49,"y":183,"z":0,"images":["grass.edge3.e"]},{"x":43,"y":181,"z":0,"images":["grass.edge3.n"]},{"x":41,"y":183,"z":0,"images":["grass.edge3.w"]},{"x":43,"y":189,"z":0,"images":["grass.edge3.s"]},{"x":45,"y":187,"z":0,"images":["grass.edge3.e"]},{"x":39,"y":185,"z":0,"images":["grass.edge3.n"]},{"x":39,"y":189,"z":0,"images":["grass.edge3.s"]},{"x":35,"y":185,"z":0,"images":["grass.edge3.n"]},{"x":33,"y":187,"z":0,"images":["grass.edge3.w"]},{"x":35,"y":193,"z":0,"images":["grass.edge3.s"]},{"x":37,"y":191,"z":0,"images":["grass.edge3.e"]},{"x":35,"y":197,"z":0,"images":["grass.edge3.n"]},{"x":23,"y":197,"z":0,"images":["grass.edge3.n"]},{"x":27,"y":193,"z":0,"images":["grass.edge3.n"]},{"x":25,"y":195,"z":0,"images":["grass.edge3.w"]},{"x":31,"y":189,"z":0,"images":["grass.edge3.n"]},{"x":29,"y":191,"z":0,"images":["grass.edge3.w"]},{"x":33,"y":195,"z":0,"images":["grass.edge3.e"]},{"x":33,"y":147,"z":0,"images":["grass.edge3.w"]},{"x":39,"y":149,"z":0,"images":["grass.edge3.s"]},{"x":41,"y":147,"z":0,"images":["grass.edge3.e"]},{"x":33,"y":143,"z":0,"images":["grass.edge3.w"]},{"x":39,"y":141,"z":0,"images":["grass.edge3.n"]},{"x":37,"y":139,"z":0,"images":["grass.edge3.e"]},{"x":33,"y":139,"z":0,"images":["grass.edge3.w"]},{"x":37,"y":111,"z":0,"images":["grass.edge3.w"]},{"x":27,"y":133,"z":0,"images":["grass.edge3.s"]},{"x":25,"y":131,"z":0,"images":["grass.edge3.w"]},{"x":31,"y":137,"z":0,"images":["grass.edge3.s"]},{"x":29,"y":135,"z":0,"images":["grass.edge3.w"]},{"x":37,"y":75,"z":0,"images":["grass.edge3.w"]},{"x":39,"y":65,"z":0,"images":["grass.edge3.n"]},{"x":35,"y":73,"z":0,"images":["grass.edge3.s"]},{"x":33,"y":71,"z":0,"images":["grass.edge3.w"]},{"x":31,"y":61,"z":0,"images":["grass.edge3.n"]},{"x":33,"y":63,"z":0,"images":["grass.edge3.e"]},{"x":29,"y":63,"z":0,"images":["grass.edge3.w"]},{"x":31,"y":69,"z":0,"images":["grass.edge3.s"]},{"x":29,"y":67,"z":0,"images":["grass.edge3.w"]},{"x":35,"y":65,"z":0,"images":["grass.edge3.n"]},{"x":47,"y":61,"z":0,"images":["grass.edge3.n"]},{"x":49,"y":63,"z":0,"images":["grass.edge3.e"]},{"x":55,"y":53,"z":0,"images":["grass.edge3.n"]},{"x":53,"y":55,"z":0,"images":["grass.edge3.w"]},{"x":59,"y":53,"z":0,"images":["grass.edge3.n"]},{"x":59,"y":57,"z":0,"images":["grass.edge3.s"]},{"x":61,"y":55,"z":0,"images":["grass.edge3.e"]},{"x":51,"y":65,"z":0,"images":["grass.edge3.n"]},{"x":57,"y":71,"z":0,"images":["grass.edge3.e"]},{"x":51,"y":85,"z":0,"images":["grass.edge3.s"]},{"x":53,"y":83,"z":0,"images":["grass.edge3.e"]},{"x":57,"y":75,"z":0,"images":["grass.edge3.e"]},{"x":55,"y":81,"z":0,"images":["grass.edge3.s"]},{"x":59,"y":77,"z":0,"images":["grass.edge3.n"]},{"x":59,"y":81,"z":0,"images":["grass.edge3.s"]},{"x":63,"y":77,"z":0,"images":["grass.edge3.n"]},{"x":63,"y":85,"z":0,"images":["grass.edge3.s"]},{"x":61,"y":83,"z":0,"images":["grass.edge3.w"]},{"x":67,"y":77,"z":0,"images":["grass.edge3.n"]},{"x":67,"y":85,"z":0,"images":["grass.edge3.s"]},{"x":71,"y":85,"z":0,"images":["grass.edge3.s"]},{"x":73,"y":83,"z":0,"images":["grass.edge3.e"]},{"x":71,"y":77,"z":0,"images":["grass.edge3.n"]},{"x":75,"y":81,"z":0,"images":["grass.edge3.s"]},{"x":77,"y":79,"z":0,"images":["grass.edge3.e"]},{"x":75,"y":73,"z":0,"images":["grass.edge3.n"]},{"x":73,"y":75,"z":0,"images":["grass.edge3.w"]},{"x":79,"y":77,"z":0,"images":["grass.edge3.s"]},{"x":81,"y":75,"z":0,"images":["grass.edge3.e"]},{"x":81,"y":71,"z":0,"images":["grass.edge3.e"]},{"x":77,"y":71,"z":0,"images":["grass.edge3.w"]},{"x":81,"y":67,"z":0,"images":["grass.edge3.e"]},{"x":77,"y":67,"z":0,"images":["grass.edge3.w"]},{"x":77,"y":63,"z":0,"images":["grass.edge3.w"]},{"x":83,"y":65,"z":0,"images":["grass.edge3.s"]},{"x":85,"y":63,"z":0,"images":["grass.edge3.e"]},{"x":77,"y":59,"z":0,"images":["grass.edge3.w"]},{"x":83,"y":57,"z":0,"images":["grass.edge3.n"]},{"x":85,"y":59,"z":0,"images":["grass.edge3.e"]},{"x":81,"y":55,"z":0,"images":["grass.edge3.e"]},{"x":77,"y":55,"z":0,"images":["grass.edge3.w"]},{"x":75,"y":53,"z":0,"images":["grass.edge3.s"]},{"x":73,"y":51,"z":0,"images":["grass.edge3.w"]},{"x":79,"y":49,"z":0,"images":["grass.edge3.n"]},{"x":81,"y":51,"z":0,"images":["grass.edge3.e"]},{"x":77,"y":47,"z":0,"images":["grass.edge3.e"]},{"x":73,"y":47,"z":0,"images":["grass.edge3.w"]},{"x":71,"y":45,"z":0,"images":["grass.edge3.s"]},{"x":69,"y":43,"z":0,"images":["grass.edge3.w"]},{"x":75,"y":41,"z":0,"images":["grass.edge3.n"]},{"x":77,"y":43,"z":0,"images":["grass.edge3.e"]},{"x":73,"y":39,"z":0,"images":["grass.edge3.e"]},{"x":69,"y":39,"z":0,"images":["grass.edge3.w"]},{"x":71,"y":33,"z":0,"images":["grass.edge3.n"]},{"x":73,"y":35,"z":0,"images":["grass.edge3.e"]},{"x":67,"y":37,"z":0,"images":["grass.edge3.s"]},{"x":65,"y":35,"z":0,"images":["grass.edge3.w"]},{"x":67,"y":29,"z":0,"images":["grass.edge3.n"]},{"x":69,"y":31,"z":0,"images":["grass.edge3.e"]},{"x":65,"y":27,"z":0,"images":["grass.edge3.e"]},{"x":61,"y":27,"z":0,"images":["grass.edge3.w"]},{"x":59,"y":25,"z":0,"images":["grass.edge3.s"]},{"x":57,"y":23,"z":0,"images":["grass.edge3.w"]},{"x":63,"y":21,"z":0,"images":["grass.edge3.n"]},{"x":65,"y":23,"z":0,"images":["grass.edge3.e"]},{"x":59,"y":17,"z":0,"images":["grass.edge3.n"]},{"x":61,"y":19,"z":0,"images":["grass.edge3.e"]},{"x":55,"y":13,"z":0,"images":["grass.edge3.n"]},{"x":57,"y":15,"z":0,"images":["grass.edge3.e"]},{"x":55,"y":21,"z":0,"images":["grass.edge3.s"]},{"x":51,"y":13,"z":0,"images":["grass.edge3.n"]},{"x":51,"y":21,"z":0,"images":["grass.edge3.s"]},{"x":47,"y":9,"z":0,"images":["grass.edge3.n"]},{"x":49,"y":11,"z":0,"images":["grass.edge3.e"]},{"x":45,"y":11,"z":0,"images":["grass.edge3.w"]},{"x":43,"y":13,"z":0,"images":["grass.edge3.n"]},{"x":41,"y":15,"z":0,"images":["grass.edge3.w"]},{"x":49,"y":23,"z":0,"images":["grass.edge3.e"]},{"x":47,"y":29,"z":0,"images":["grass.edge3.s"]},{"x":49,"y":27,"z":0,"images":["grass.edge3.e"]},{"x":41,"y":19,"z":0,"images":["grass.edge3.w"]},{"x":43,"y":29,"z":0,"images":["grass.edge3.s"]},{"x":39,"y":21,"z":0,"images":["grass.edge3.n"]},{"x":39,"y":29,"z":0,"images":["grass.edge3.s"]},{"x":35,"y":21,"z":0,"images":["grass.edge3.n"]},{"x":33,"y":23,"z":0,"images":["grass.edge3.w"]},{"x":35,"y":29,"z":0,"images":["grass.edge3.s"]},{"x":31,"y":25,"z":0,"images":["grass.edge3.n"]},{"x":29,"y":27,"z":0,"images":["grass.edge3.w"]},{"x":31,"y":33,"z":0,"images":["grass.edge3.s"]},{"x":33,"y":31,"z":0,"images":["grass.edge3.e"]},{"x":11,"y":29,"z":0,"images":["grass.edge3.s"]},{"x":9,"y":27,"z":0,"images":["grass.edge3.w"]},{"x":15,"y":25,"z":0,"images":["grass.edge3.n"]},{"x":17,"y":27,"z":0,"images":["grass.edge3.e"]},{"x":13,"y":23,"z":0,"images":["grass.edge3.e"]},{"x":9,"y":23,"z":0,"images":["grass.edge3.w"]},{"x":11,"y":17,"z":0,"images":["grass.edge3.n"]},{"x":13,"y":19,"z":0,"images":["grass.edge3.e"]},{"x":-3,"y":3,"z":0,"images":["grass.edge3.e"]},{"x":-3,"y":19,"z":0,"images":["grass.edge3.e"]},{"x":-1,"y":5,"z":0,"images":["grass.edge3.n"]},{"x":1,"y":7,"z":0,"images":["grass.edge3.e"]},{"x":-1,"y":17,"z":0,"images":["grass.edge3.s"]},{"x":3,"y":9,"z":0,"images":["grass.edge3.n"]},{"x":3,"y":17,"z":0,"images":["grass.edge3.s"]},{"x":7,"y":9,"z":0,"images":["grass.edge3.n"]},{"x":9,"y":11,"z":0,"images":["grass.edge3.e"]},{"x":9,"y":15,"z":0,"images":["grass.edge3.e"]},{"x":7,"y":21,"z":0,"images":["grass.edge3.s"]},{"x":5,"y":19,"z":0,"images":["grass.edge3.w"]},{"x":13,"y":31,"z":0,"images":["grass.edge3.w"]},{"x":15,"y":37,"z":0,"images":["grass.edge3.s"]},{"x":13,"y":35,"z":0,"images":["grass.edge3.w"]},{"x":19,"y":29,"z":0,"images":["grass.edge3.n"]},{"x":21,"y":31,"z":0,"images":["grass.edge3.e"]},{"x":27,"y":29,"z":0,"images":["grass.edge3.n"]},{"x":25,"y":31,"z":0,"images":["grass.edge3.w"]},{"x":19,"y":41,"z":0,"images":["grass.edge3.s"]},{"x":17,"y":39,"z":0,"images":["grass.edge3.w"]},{"x":23,"y":33,"z":0,"images":["grass.edge3.n"]},{"x":23,"y":41,"z":0,"images":["grass.edge3.s"]},{"x":29,"y":35,"z":0,"images":["grass.edge3.e"]},{"x":27,"y":41,"z":0,"images":["grass.edge3.s"]},{"x":29,"y":39,"z":0,"images":["grass.edge3.e"]},{"x":37,"y":135,"z":0,"images":["grass.edge2.e"]},{"x":41,"y":119,"z":0,"images":["grass.edge2.e"]},{"x":39,"y":121,"z":0,"images":["grass.edge1.n"]},{"x":41,"y":123,"z":0,"images":["grass.edge1.e"]},{"x":43,"y":117,"z":0,"images":["grass.edge1.s"]},{"x":43,"y":125,"z":0,"images":["grass.edge2.n"]},{"x":43,"y":129,"z":0,"images":["grass.edge2.s"]},{"x":45,"y":127,"z":0,"images":["grass.edge2.e"]},{"x":39,"y":117,"z":0,"images":["grass.edge3.s"]},{"x":35,"y":113,"z":0,"images":["grass.edge3.n"]},{"x":33,"y":115,"z":0,"images":["grass.edge3.w"]},{"x":27,"y":121,"z":0,"images":["grass.edge3.n"]},{"x":25,"y":123,"z":0,"images":["grass.edge3.w"]},{"x":25,"y":127,"z":0,"images":["grass.edge3.w"]},{"x":31,"y":117,"z":0,"images":["grass.edge3.n"]},{"x":29,"y":119,"z":0,"images":["grass.edge3.w"]},{"x":37,"y":119,"z":0,"images":["grass.edge3.e"]},{"x":37,"y":123,"z":0,"images":["grass.edge3.e"]},{"x":39,"y":125,"z":0,"images":["grass.edge3.n"]},{"x":39,"y":133,"z":0,"images":["grass.edge3.s"]},{"x":41,"y":131,"z":0,"images":["grass.edge3.e"]},{"x":71,"y":145,"z":0,"images":["grass.edge2.s"]},{"x":73,"y":143,"z":0,"images":["grass.edge2.e"]},{"x":73,"y":139,"z":0,"images":["grass.edge2.e"]},{"x":61,"y":131,"z":0,"images":["grass.edge2.w"]},{"x":61,"y":135,"z":0,"images":["grass.edge2.w"]},{"x":75,"y":137,"z":0,"images":["grass.edge2.s"]},{"x":77,"y":135,"z":0,"images":["grass.edge2.e"]},{"x":77,"y":131,"z":0,"images":["grass.edge2.e"]},{"x":75,"y":125,"z":0,"images":["grass.edge1.n"]},{"x":77,"y":127,"z":0,"images":["grass.edge1.e"]},{"x":55,"y":97,"z":0,"images":["grass.edge1.n"]},{"x":55,"y":101,"z":0,"images":["grass.edge1.s"]},{"x":53,"y":99,"z":0,"images":["grass.edge1.w"]},{"x":59,"y":97,"z":0,"images":["grass.edge1.n"]},{"x":61,"y":99,"z":0,"images":["grass.edge1.e"]},{"x":57,"y":103,"z":0,"images":["grass.edge2.w"]},{"x":63,"y":101,"z":0,"images":["grass.edge1.n"]},{"x":65,"y":103,"z":0,"images":["grass.edge1.e"]},{"x":59,"y":109,"z":0,"images":["grass.edge2.s"]},{"x":57,"y":107,"z":0,"images":["grass.edge2.w"]},{"x":67,"y":105,"z":0,"images":["grass.edge2.n"]},{"x":69,"y":107,"z":0,"images":["grass.edge2.e"]},{"x":61,"y":111,"z":0,"images":["grass.edge2.w"]},{"x":69,"y":111,"z":0,"images":["grass.edge2.e"]},{"x":63,"y":117,"z":0,"images":["grass.edge2.s"]},{"x":61,"y":115,"z":0,"images":["grass.edge2.w"]},{"x":71,"y":113,"z":0,"images":["grass.edge2.n"]},{"x":73,"y":115,"z":0,"images":["grass.edge2.e"]},{"x":63,"y":121,"z":0,"images":["grass.edge2.n"]},{"x":61,"y":123,"z":0,"images":["grass.edge2.w"]},{"x":61,"y":127,"z":0,"images":["grass.edge1.w"]},{"x":65,"y":119,"z":0,"images":["grass.edge2.w"]},{"x":73,"y":119,"z":0,"images":["grass.edge2.e"]},{"x":73,"y":123,"z":0,"images":["grass.edge1.e"]},{"x":59,"y":137,"z":0,"images":["grass.edge2.n"]},{"x":57,"y":139,"z":0,"images":["grass.edge2.w"]},{"x":57,"y":143,"z":0,"images":["grass.edge2.w"]},{"x":67,"y":145,"z":0,"images":["grass.edge1.s"]},{"x":63,"y":169,"z":0,"images":["grass.edge2.s"]},{"x":65,"y":167,"z":0,"images":["grass.edge2.e"]},{"x":61,"y":167,"z":0,"images":["grass.edge2.w"]},{"x":65,"y":163,"z":0,"images":["grass.edge1.e"]},{"x":61,"y":163,"z":0,"images":["grass.edge1.w"]},{"x":59,"y":161,"z":0,"images":["grass.edge2.s"]},{"x":57,"y":159,"z":0,"images":["grass.edge2.w"]},{"x":65,"y":159,"z":0,"images":["grass.edge1.e"]},{"x":65,"y":147,"z":0,"images":["grass.edge1.e"]},{"x":65,"y":151,"z":0,"images":["grass.edge1.e"]},{"x":65,"y":155,"z":0,"images":["grass.edge2.e"]},{"x":57,"y":155,"z":0,"images":["grass.edge1.w"]},{"x":55,"y":145,"z":0,"images":["grass.edge1.n"]},{"x":53,"y":147,"z":0,"images":["grass.edge1.w"]},{"x":55,"y":153,"z":0,"images":["grass.edge2.s"]},{"x":47,"y":149,"z":0,"images":["grass.edge1.n"]},{"x":47,"y":153,"z":0,"images":["grass.edge1.s"]},{"x":45,"y":151,"z":0,"images":["grass.edge1.w"]},{"x":51,"y":149,"z":0,"images":["grass.edge2.n"]},{"x":51,"y":153,"z":0,"images":["grass.edge2.s"]},{"x":11,"y":185,"z":0,"images":["grass.edge2.s"]},{"x":13,"y":183,"z":0,"images":["grass.edge2.e"]},{"x":19,"y":173,"z":0,"images":["grass.edge2.s"]},{"x":21,"y":171,"z":0,"images":["grass.edge2.e"]},{"x":11,"y":173,"z":0,"images":["grass.edge1.n"]},{"x":9,"y":175,"z":0,"images":["grass.edge1.w"]},{"x":13,"y":179,"z":0,"images":["grass.edge1.e"]},{"x":9,"y":179,"z":0,"images":["grass.edge1.w"]},{"x":13,"y":171,"z":0,"images":["grass.edge1.w"]},{"x":15,"y":177,"z":0,"images":["grass.edge1.s"]},{"x":17,"y":175,"z":0,"images":["grass.edge1.e"]},{"x":13,"y":167,"z":0,"images":["grass.edge2.w"]},{"x":21,"y":167,"z":0,"images":["grass.edge1.e"]},{"x":13,"y":163,"z":0,"images":["grass.edge1.w"]},{"x":21,"y":163,"z":0,"images":["grass.edge1.e"]},{"x":15,"y":157,"z":0,"images":["grass.edge1.n"]},{"x":13,"y":159,"z":0,"images":["grass.edge1.w"]},{"x":21,"y":159,"z":0,"images":["grass.edge1.e"]},{"x":21,"y":155,"z":0,"images":["grass.edge2.e"]},{"x":17,"y":155,"z":0,"images":["grass.edge2.w"]},{"x":21,"y":151,"z":0,"images":["grass.edge2.e"]},{"x":17,"y":151,"z":0,"images":["grass.edge2.w"]},{"x":21,"y":147,"z":0,"images":["grass.edge1.e"]},{"x":17,"y":147,"z":0,"images":["grass.edge1.w"]},{"x":19,"y":133,"z":0,"images":["grass.edge1.n"]},{"x":21,"y":135,"z":0,"images":["grass.edge1.e"]},{"x":17,"y":139,"z":0,"images":["grass.edge2.w"]},{"x":17,"y":143,"z":0,"images":["grass.edge2.w"]},{"x":23,"y":137,"z":0,"images":["grass.edge1.n"]},{"x":25,"y":139,"z":0,"images":["grass.edge1.e"]},{"x":23,"y":145,"z":0,"images":["grass.edge1.s"]},{"x":25,"y":143,"z":0,"images":["grass.edge1.e"]},{"x":7,"y":117,"z":0,"images":["grass.edge1.n"]},{"x":5,"y":119,"z":0,"images":["grass.edge1.w"]},{"x":11,"y":121,"z":0,"images":["grass.edge1.s"]},{"x":13,"y":119,"z":0,"images":["grass.edge1.e"]},{"x":15,"y":137,"z":0,"images":["grass.edge1.s"]},{"x":13,"y":135,"z":0,"images":["grass.edge1.w"]},{"x":9,"y":123,"z":0,"images":["grass.edge2.e"]},{"x":5,"y":123,"z":0,"images":["grass.edge2.w"]},{"x":7,"y":129,"z":0,"images":["grass.edge1.s"]},{"x":5,"y":127,"z":0,"images":["grass.edge1.w"]},{"x":11,"y":125,"z":0,"images":["grass.edge2.n"]},{"x":13,"y":127,"z":0,"images":["grass.edge2.e"]},{"x":11,"y":133,"z":0,"images":["grass.edge1.s"]},{"x":9,"y":131,"z":0,"images":["grass.edge1.w"]},{"x":15,"y":129,"z":0,"images":["grass.edge1.n"]},{"x":17,"y":131,"z":0,"images":["grass.edge1.e"]},{"x":13,"y":115,"z":0,"images":["grass.edge1.e"]},{"x":9,"y":115,"z":0,"images":["grass.edge1.w"]},{"x":7,"y":109,"z":0,"images":["grass.edge1.n"]},{"x":7,"y":113,"z":0,"images":["grass.edge1.s"]},{"x":5,"y":111,"z":0,"images":["grass.edge1.w"]},{"x":13,"y":111,"z":0,"images":["grass.edge2.e"]},{"x":11,"y":105,"z":0,"images":["grass.edge1.n"]},{"x":9,"y":107,"z":0,"images":["grass.edge1.w"]},{"x":15,"y":109,"z":0,"images":["grass.edge1.s"]},{"x":17,"y":107,"z":0,"images":["grass.edge1.e"]},{"x":11,"y":93,"z":0,"images":["grass.edge2.n"]},{"x":9,"y":95,"z":0,"images":["grass.edge2.w"]},{"x":11,"y":101,"z":0,"images":["grass.edge2.s"]},{"x":9,"y":99,"z":0,"images":["grass.edge2.w"]},{"x":13,"y":103,"z":0,"images":["grass.edge1.w"]},{"x":19,"y":105,"z":0,"images":["grass.edge1.s"]},{"x":21,"y":103,"z":0,"images":["grass.edge1.e"]},{"x":23,"y":101,"z":0,"images":["grass.edge2.s"]},{"x":25,"y":99,"z":0,"images":["grass.edge2.e"]},{"x":25,"y":95,"z":0,"images":["grass.edge2.e"]},{"x":15,"y":69,"z":0,"images":["grass.edge1.s"]},{"x":13,"y":67,"z":0,"images":["grass.edge1.w"]},{"x":19,"y":65,"z":0,"images":["grass.edge2.n"]},{"x":21,"y":67,"z":0,"images":["grass.edge2.e"]},{"x":21,"y":71,"z":0,"images":["grass.edge2.e"]},{"x":17,"y":71,"z":0,"images":["grass.edge2.w"]},{"x":21,"y":75,"z":0,"images":["grass.edge1.e"]},{"x":17,"y":75,"z":0,"images":["grass.edge1.w"]},{"x":15,"y":89,"z":0,"images":["grass.edge1.n"]},{"x":13,"y":91,"z":0,"images":["grass.edge1.w"]},{"x":25,"y":91,"z":0,"images":["grass.edge1.e"]},{"x":21,"y":79,"z":0,"images":["grass.edge2.e"]},{"x":17,"y":79,"z":0,"images":["grass.edge2.w"]},{"x":21,"y":83,"z":0,"images":["grass.edge2.e"]},{"x":17,"y":83,"z":0,"images":["grass.edge2.w"]},{"x":17,"y":87,"z":0,"images":["grass.edge2.w"]},{"x":23,"y":85,"z":0,"images":["grass.edge1.n"]},{"x":25,"y":87,"z":0,"images":["grass.edge1.e"]},{"x":17,"y":63,"z":0,"images":["grass.edge2.e"]},{"x":13,"y":63,"z":0,"images":["grass.edge2.w"]},{"x":11,"y":57,"z":0,"images":["grass.edge1.n"]},{"x":11,"y":61,"z":0,"images":["grass.edge1.s"]},{"x":9,"y":59,"z":0,"images":["grass.edge1.w"]},{"x":15,"y":53,"z":0,"images":["grass.edge1.n"]},{"x":13,"y":55,"z":0,"images":["grass.edge1.w"]},{"x":17,"y":59,"z":0,"images":["grass.edge2.e"]},{"x":39,"y":45,"z":0,"images":["grass.edge2.n"]},{"x":39,"y":49,"z":0,"images":["grass.edge2.s"]},{"x":35,"y":45,"z":0,"images":["grass.edge1.n"]},{"x":33,"y":47,"z":0,"images":["grass.edge1.w"]},{"x":35,"y":53,"z":0,"images":["grass.edge2.s"]},{"x":37,"y":51,"z":0,"images":["grass.edge2.e"]},{"x":31,"y":49,"z":0,"images":["grass.edge1.n"]},{"x":31,"y":53,"z":0,"images":["grass.edge1.s"]},{"x":19,"y":53,"z":0,"images":["grass.edge1.n"]},{"x":19,"y":57,"z":0,"images":["grass.edge1.s"]},{"x":23,"y":49,"z":0,"images":["grass.edge1.n"]},{"x":21,"y":51,"z":0,"images":["grass.edge1.w"]},{"x":23,"y":57,"z":0,"images":["grass.edge2.s"]},{"x":25,"y":55,"z":0,"images":["grass.edge2.e"]},{"x":27,"y":49,"z":0,"images":["grass.edge1.n"]},{"x":27,"y":53,"z":0,"images":["grass.edge1.s"]},{"x":39,"y":37,"z":0,"images":["grass.edge1.n"]},{"x":39,"y":41,"z":0,"images":["grass.edge1.s"]},{"x":37,"y":39,"z":0,"images":["grass.edge1.w"]},{"x":63,"y":33,"z":0,"images":["grass.edge2.s"]},{"x":61,"y":31,"z":0,"images":["grass.edge2.w"]},{"x":59,"y":33,"z":0,"images":["grass.edge2.n"]},{"x":61,"y":35,"z":0,"images":["grass.edge2.e"]},{"x":55,"y":29,"z":0,"images":["grass.edge2.n"]},{"x":57,"y":31,"z":0,"images":["grass.edge2.e"]},{"x":53,"y":31,"z":0,"images":["grass.edge2.w"]},{"x":47,"y":33,"z":0,"images":["grass.edge1.n"]},{"x":45,"y":35,"z":0,"images":["grass.edge1.w"]},{"x":51,"y":33,"z":0,"images":["grass.edge1.n"]},{"x":43,"y":37,"z":0,"images":["grass.edge2.n"]},{"x":41,"y":43,"z":0,"images":["grass.edge1.w"]},{"x":43,"y":49,"z":0,"images":["grass.edge2.s"]},{"x":45,"y":47,"z":0,"images":["grass.edge2.e"]},{"x":47,"y":45,"z":0,"images":["grass.edge1.s"]},{"x":51,"y":49,"z":0,"images":["grass.edge1.s"]},{"x":53,"y":47,"z":0,"images":["grass.edge1.e"]},{"x":49,"y":47,"z":0,"images":["grass.edge1.w"]},{"x":61,"y":39,"z":0,"images":["grass.edge2.e"]},{"x":55,"y":45,"z":0,"images":["grass.edge2.s"]},{"x":61,"y":43,"z":0,"images":["grass.edge2.e"]},{"x":59,"y":49,"z":0,"images":["grass.edge1.s"]},{"x":61,"y":47,"z":0,"images":["grass.edge1.e"]},{"x":57,"y":47,"z":0,"images":["grass.edge1.w"]},{"x":67,"y":53,"z":0,"images":["grass.edge2.n"]},{"x":69,"y":55,"z":0,"images":["grass.edge2.e"]},{"x":65,"y":55,"z":0,"images":["grass.edge2.w"]},{"x":67,"y":61,"z":0,"images":["grass.edge2.s"]},{"x":65,"y":59,"z":0,"images":["grass.edge2.w"]},{"x":71,"y":57,"z":0,"images":["grass.edge1.n"]},{"x":73,"y":59,"z":0,"images":["grass.edge1.e"]},{"x":73,"y":63,"z":0,"images":["grass.edge2.e"]},{"x":69,"y":63,"z":0,"images":["grass.edge2.w"]},{"x":63,"y":69,"z":0,"images":["grass.edge1.n"]},{"x":63,"y":73,"z":0,"images":["grass.edge1.s"]},{"x":61,"y":71,"z":0,"images":["grass.edge1.w"]},{"x":67,"y":65,"z":0,"images":["grass.edge2.n"]},{"x":65,"y":67,"z":0,"images":["grass.edge2.w"]},{"x":67,"y":73,"z":0,"images":["grass.edge2.s"]},{"x":69,"y":71,"z":0,"images":["grass.edge2.e"]},{"x":71,"y":69,"z":0,"images":["grass.edge2.s"]},{"x":73,"y":67,"z":0,"images":["grass.edge2.e"]},{"x":57,"y":59,"z":0,"images":["grass.edge3.e"]},{"x":53,"y":59,"z":0,"images":["grass.edge3.w"]},{"x":53,"y":63,"z":0,"images":["grass.edge3.w"]},{"x":59,"y":61,"z":0,"images":["grass.edge3.n"]},{"x":59,"y":69,"z":0,"images":["grass.edge3.s"]},{"x":61,"y":67,"z":0,"images":["grass.edge3.e"]},{"x":63,"y":61,"z":0,"images":["grass.edge3.n"]},{"x":63,"y":65,"z":0,"images":["grass.edge3.s"]},{"x":65,"y":63,"z":0,"images":["grass.edge3.e"]},{"x":7,"y":181,"z":0,"images":["grass.edge2.n"]},{"x":5,"y":183,"z":0,"images":["grass.edge2.w"]},{"x":3,"y":185,"z":0,"images":["grass.edge2.n"]},{"x":1,"y":187,"z":0,"images":["grass.edge2.w"]},{"x":9,"y":187,"z":0,"images":["grass.edge1.e"]},{"x":-1,"y":197,"z":0,"images":["grass.edge1.n"]},{"x":1,"y":191,"z":0,"images":["grass.edge1.w"]},{"x":5,"y":195,"z":0,"images":["grass.edge2.e"]},{"x":1,"y":195,"z":0,"images":["grass.edge2.w"]},{"x":7,"y":193,"z":0,"images":["grass.edge1.s"]},{"x":9,"y":191,"z":0,"images":["grass.edge1.e"]},{"x":7,"y":197,"z":0,"images":["grass.edge2.n"]},{"x":73,"y":15,"z":0,"images":["grass.edge1.w"]},{"x":73,"y":19,"z":0,"images":["grass.edge2.w"]},{"x":75,"y":25,"z":0,"images":["grass.edge1.s"]},{"x":73,"y":23,"z":0,"images":["grass.edge1.w"]},{"x":79,"y":29,"z":0,"images":["grass.edge1.s"]},{"x":77,"y":27,"z":0,"images":["grass.edge1.w"]},{"x":83,"y":29,"z":0,"images":["grass.edge1.s"]},{"x":87,"y":29,"z":0,"images":["grass.edge1.s"]},{"x":89,"y":27,"z":0,"images":["grass.edge1.e"]},{"x":71,"y":1,"z":0,"images":["grass.edge1.n"]},{"x":73,"y":3,"z":0,"images":["grass.edge1.e"]},{"x":69,"y":3,"z":0,"images":["grass.edge1.w"]},{"x":71,"y":9,"z":0,"images":["grass.edge1.s"]},{"x":69,"y":7,"z":0,"images":["grass.edge1.w"]},{"x":75,"y":5,"z":0,"images":["grass.edge2.n"]},{"x":73,"y":11,"z":0,"images":["grass.edge2.w"]},{"x":79,"y":5,"z":0,"images":["grass.edge1.n"]},{"x":83,"y":5,"z":0,"images":["grass.edge1.n"]},{"x":87,"y":5,"z":0,"images":["grass.edge2.n"]},{"x":91,"y":5,"z":0,"images":["grass.edge2.n"]},{"x":93,"y":7,"z":0,"images":["grass.edge2.e"]},{"x":93,"y":11,"z":0,"images":["grass.edge2.e"]},{"x":89,"y":23,"z":0,"images":["grass.edge2.e"]},{"x":93,"y":15,"z":0,"images":["grass.edge1.e"]},{"x":91,"y":21,"z":0,"images":["grass.edge1.s"]},{"x":95,"y":17,"z":0,"images":["grass.edge1.n"]},{"x":97,"y":19,"z":0,"images":["grass.edge1.e"]},{"x":97,"y":23,"z":0,"images":["grass.edge1.e"]},{"x":93,"y":23,"z":0,"images":["grass.edge1.w"]},{"x":97,"y":27,"z":0,"images":["grass.edge1.e"]},{"x":93,"y":27,"z":0,"images":["grass.edge1.w"]},{"x":97,"y":31,"z":0,"images":["grass.edge1.e"]},{"x":93,"y":31,"z":0,"images":["grass.edge1.w"]},{"x":95,"y":37,"z":0,"images":["grass.edge1.s"]},{"x":97,"y":35,"z":0,"images":["grass.edge1.e"]},{"x":91,"y":33,"z":0,"images":["grass.edge1.n"]},{"x":89,"y":35,"z":0,"images":["grass.edge1.w"]},{"x":87,"y":37,"z":0,"images":["grass.edge1.n"]},{"x":85,"y":39,"z":0,"images":["grass.edge1.w"]},{"x":93,"y":39,"z":0,"images":["grass.edge1.e"]},{"x":85,"y":43,"z":0,"images":["grass.edge2.w"]},{"x":93,"y":43,"z":0,"images":["grass.edge1.e"]},{"x":87,"y":49,"z":0,"images":["grass.edge1.s"]},{"x":85,"y":47,"z":0,"images":["grass.edge1.w"]},{"x":93,"y":47,"z":0,"images":["grass.edge2.e"]},{"x":93,"y":51,"z":0,"images":["grass.edge1.e"]},{"x":89,"y":51,"z":0,"images":["grass.edge1.w"]},{"x":89,"y":55,"z":0,"images":["grass.edge2.w"]},{"x":95,"y":53,"z":0,"images":["grass.edge1.n"]},{"x":97,"y":55,"z":0,"images":["grass.edge1.e"]},{"x":89,"y":59,"z":0,"images":["grass.edge2.w"]},{"x":97,"y":59,"z":0,"images":["grass.edge1.e"]},{"x":91,"y":65,"z":0,"images":["grass.edge1.s"]},{"x":89,"y":63,"z":0,"images":["grass.edge1.w"]},{"x":97,"y":63,"z":0,"images":["grass.edge1.e"]},{"x":97,"y":67,"z":0,"images":["grass.edge1.e"]},{"x":93,"y":67,"z":0,"images":["grass.edge1.w"]},{"x":97,"y":71,"z":0,"images":["grass.edge1.e"]},{"x":93,"y":71,"z":0,"images":["grass.edge1.w"]},{"x":97,"y":75,"z":0,"images":["grass.edge1.e"]},{"x":93,"y":75,"z":0,"images":["grass.edge1.w"]},{"x":83,"y":81,"z":0,"images":["grass.edge1.n"]},{"x":81,"y":83,"z":0,"images":["grass.edge1.w"]},{"x":81,"y":87,"z":0,"images":["grass.edge1.w"]},{"x":87,"y":77,"z":0,"images":["grass.edge2.n"]},{"x":85,"y":79,"z":0,"images":["grass.edge2.w"]},{"x":91,"y":77,"z":0,"images":["grass.edge2.n"]},{"x":95,"y":81,"z":0,"images":["grass.edge1.s"]},{"x":97,"y":79,"z":0,"images":["grass.edge1.e"]},{"x":93,"y":83,"z":0,"images":["grass.edge2.e"]},{"x":93,"y":87,"z":0,"images":["grass.edge1.e"]},{"x":93,"y":91,"z":0,"images":["grass.edge1.e"]},{"x":93,"y":95,"z":0,"images":["grass.edge2.e"]},{"x":93,"y":99,"z":0,"images":["grass.edge2.e"]},{"x":71,"y":93,"z":0,"images":["grass.edge2.n"]},{"x":71,"y":97,"z":0,"images":["grass.edge2.s"]},{"x":69,"y":95,"z":0,"images":["grass.edge2.w"]},{"x":81,"y":91,"z":0,"images":["grass.edge2.w"]},{"x":75,"y":93,"z":0,"images":["grass.edge2.n"]},{"x":79,"y":93,"z":0,"images":["grass.edge2.n"]},{"x":75,"y":101,"z":0,"images":["grass.edge2.s"]},{"x":73,"y":99,"z":0,"images":["grass.edge2.w"]},{"x":77,"y":103,"z":0,"images":["grass.edge2.w"]},{"x":93,"y":103,"z":0,"images":["grass.edge2.e"]},{"x":93,"y":107,"z":0,"images":["grass.edge1.e"]},{"x":93,"y":111,"z":0,"images":["grass.edge1.e"]},{"x":93,"y":115,"z":0,"images":["grass.edge1.e"]},{"x":79,"y":109,"z":0,"images":["grass.edge1.s"]},{"x":77,"y":107,"z":0,"images":["grass.edge1.w"]},{"x":81,"y":111,"z":0,"images":["grass.edge2.w"]},{"x":81,"y":115,"z":0,"images":["grass.edge1.w"]},{"x":87,"y":117,"z":0,"images":["grass.edge1.s"]},{"x":85,"y":119,"z":0,"images":["grass.edge1.e"]},{"x":81,"y":119,"z":0,"images":["grass.edge1.w"]},{"x":93,"y":119,"z":0,"images":["grass.edge2.e"]},{"x":89,"y":119,"z":0,"images":["grass.edge2.w"]},{"x":83,"y":125,"z":0,"images":["grass.edge2.s"]},{"x":81,"y":123,"z":0,"images":["grass.edge2.w"]},{"x":87,"y":121,"z":0,"images":["grass.edge2.n"]},{"x":91,"y":125,"z":0,"images":["grass.edge1.s"]},{"x":93,"y":123,"z":0,"images":["grass.edge1.e"]},{"x":89,"y":127,"z":0,"images":["grass.edge2.e"]},{"x":85,"y":127,"z":0,"images":["grass.edge2.w"]},{"x":89,"y":131,"z":0,"images":["grass.edge2.e"]},{"x":85,"y":131,"z":0,"images":["grass.edge2.w"]},{"x":87,"y":137,"z":0,"images":["grass.edge2.s"]},{"x":85,"y":135,"z":0,"images":["grass.edge2.w"]},{"x":91,"y":133,"z":0,"images":["grass.edge1.n"]},{"x":93,"y":135,"z":0,"images":["grass.edge1.e"]},{"x":91,"y":141,"z":0,"images":["grass.edge2.s"]},{"x":93,"y":139,"z":0,"images":["grass.edge2.e"]},{"x":89,"y":139,"z":0,"images":["grass.edge2.w"]}]},{"name":"object","world":[{"x":67,"y":187,"z":0,"images":["trunk"]},{"x":67,"y":187,"z":4,"images":["oak"]},{"x":73,"y":185,"z":0,"images":["trunk"]},{"x":73,"y":185,"z":4,"images":["oak"]},{"x":72,"y":189,"z":0,"images":["trunk"]},{"x":72,"y":189,"z":4,"images":["oak"]},{"x":89,"y":181,"z":0,"images":["trunk"]},{"x":89,"y":181,"z":4,"images":["oak"]},{"x":91,"y":185,"z":0,"images":["trunk"]},{"x":91,"y":185,"z":4,"images":["pine"]},{"x":86,"y":190,"z":0,"images":["trunk"]},{"x":86,"y":190,"z":4,"images":["pine"]},{"x":90,"y":190,"z":0,"images":["trunk"]},{"x":90,"y":190,"z":4,"images":["oak"]},{"x":94,"y":190,"z":0,"images":["trunk"]},{"x":94,"y":190,"z":4,"images":["pine"]},{"x":91,"y":166,"z":0,"images":["trunk"]},{"x":91,"y":166,"z":4,"images":["pine"]},{"x":91,"y":162,"z":0,"images":["trunk"]},{"x":91,"y":162,"z":4,"images":["pine"]},{"x":90,"y":158,"z":0,"images":["trunk"]},{"x":90,"y":158,"z":4,"images":["oak"]},{"x":91,"y":154,"z":0,"images":["trunk"]},{"x":91,"y":154,"z":4,"images":["oak"]},{"x":81,"y":160,"z":0,"images":["trunk"]},{"x":81,"y":160,"z":4,"images":["pine"]},{"x":81,"y":156,"z":0,"images":["trunk"]},{"x":81,"y":156,"z":4,"images":["oak"]},{"x":64,"y":165,"z":0,"images":["trunk"]},{"x":64,"y":165,"z":4,"images":["brown"]},{"x":68,"y":161,"z":0,"images":["trunk"]},{"x":68,"y":161,"z":4,"images":["pine"]},{"x":68,"y":167,"z":0,"images":["trunk"]},{"x":68,"y":167,"z":4,"images":["pine"]},{"x":67,"y":171,"z":0,"images":["trunk"]},{"x":67,"y":171,"z":4,"images":["oak"]},{"x":57,"y":176,"z":0,"images":["trunk"]},{"x":57,"y":176,"z":4,"images":["pine"]},{"x":47,"y":187,"z":0,"images":["trunk"]},{"x":47,"y":187,"z":4,"images":["oak"]},{"x":47,"y":174,"z":0,"images":["trunk"]},{"x":47,"y":174,"z":4,"images":["oak"]},{"x":22,"y":189,"z":0,"images":["trunk"]},{"x":22,"y":189,"z":4,"images":["oak"]},{"x":26,"y":186,"z":0,"images":["trunk"]},{"x":26,"y":186,"z":4,"images":["pine"]},{"x":28,"y":174,"z":0,"images":["trunk"]},{"x":28,"y":174,"z":4,"images":["oak"]},{"x":31,"y":170,"z":0,"images":["trunk"]},{"x":31,"y":170,"z":4,"images":["oak"]},{"x":33,"y":174,"z":0,"images":["trunk"]},{"x":33,"y":174,"z":4,"images":["oak"]},{"x":2,"y":183,"z":0,"images":["trunk"]},{"x":2,"y":183,"z":4,"images":["oak"]},{"x":8,"y":168,"z":0,"images":["trunk"]},{"x":8,"y":168,"z":4,"images":["pine"]},{"x":12,"y":165,"z":0,"images":["trunk"]},{"x":12,"y":165,"z":4,"images":["pine"]},{"x":16,"y":149,"z":0,"images":["trunk"]},{"x":16,"y":149,"z":4,"images":["brown"]},{"x":12,"y":149,"z":0,"images":["trunk"]},{"x":12,"y":149,"z":4,"images":["oak"]},{"x":0,"y":152,"z":0,"images":["trunk"]},{"x":0,"y":152,"z":4,"images":["oak"]},{"x":0,"y":148,"z":0,"images":["trunk"]},{"x":0,"y":148,"z":4,"images":["brown"]},{"x":1,"y":144,"z":0,"images":["trunk"]},{"x":1,"y":144,"z":4,"images":["oak"]},{"x":3,"y":138,"z":0,"images":["trunk"]},{"x":3,"y":138,"z":4,"images":["brown"]},{"x":3,"y":134,"z":0,"images":["trunk"]},{"x":3,"y":134,"z":4,"images":["oak"]},{"x":7,"y":132,"z":0,"images":["trunk"]},{"x":7,"y":132,"z":4,"images":["pine"]},{"x":9,"y":136,"z":0,"images":["trunk"]},{"x":9,"y":136,"z":4,"images":["oak"]},{"x":0,"y":126,"z":0,"images":["trunk"]},{"x":0,"y":126,"z":4,"images":["oak"]},{"x":19,"y":129,"z":0,"images":["trunk"]},{"x":19,"y":129,"z":4,"images":["oak"]},{"x":29,"y":139,"z":0,"images":["trunk"]},{"x":29,"y":139,"z":4,"images":["pine"]},{"x":38,"y":135,"z":0,"images":["trunk"]},{"x":38,"y":135,"z":4,"images":["oak"]},{"x":42,"y":118,"z":0,"images":["trunk"]},{"x":42,"y":118,"z":4,"images":["pine"]},{"x":39,"y":123,"z":0,"images":["trunk"]},{"x":39,"y":123,"z":4,"images":["oak"]},{"x":46,"y":125,"z":0,"images":["trunk"]},{"x":46,"y":125,"z":4,"images":["oak"]},{"x":33,"y":108,"z":0,"images":["trunk"]},{"x":33,"y":108,"z":4,"images":["oak"]},{"x":28,"y":114,"z":0,"images":["trunk"]},{"x":28,"y":114,"z":4,"images":["pine"]},{"x":8,"y":110,"z":0,"images":["trunk"]},{"x":8,"y":110,"z":4,"images":["oak"]},{"x":13,"y":98,"z":0,"images":["trunk"]},{"x":13,"y":98,"z":4,"images":["oak"]},{"x":9,"y":100,"z":0,"images":["trunk"]},{"x":9,"y":100,"z":4,"images":["oak"]},{"x":0,"y":95,"z":0,"images":["trunk"]},{"x":0,"y":95,"z":4,"images":["pine"]},{"x":21,"y":88,"z":0,"images":["trunk"]},{"x":21,"y":88,"z":4,"images":["oak"]},{"x":27,"y":94,"z":0,"images":["trunk"]},{"x":27,"y":94,"z":4,"images":["oak"]},{"x":32,"y":89,"z":0,"images":["trunk"]},{"x":32,"y":89,"z":4,"images":["pine"]},{"x":25,"y":69,"z":0,"images":["trunk"]},{"x":25,"y":69,"z":4,"images":["brown"]},{"x":20,"y":76,"z":0,"images":["trunk"]},{"x":20,"y":76,"z":4,"images":["oak"]},{"x":28,"y":55,"z":0,"images":["trunk"]},{"x":28,"y":55,"z":4,"images":["pine"]},{"x":22,"y":60,"z":0,"images":["trunk"]},{"x":22,"y":60,"z":4,"images":["oak"]},{"x":24,"y":56,"z":0,"images":["trunk"]},{"x":24,"y":56,"z":4,"images":["brown"]},{"x":23,"y":52,"z":0,"images":["trunk"]},{"x":23,"y":52,"z":4,"images":["pine"]},{"x":19,"y":52,"z":0,"images":["trunk"]},{"x":19,"y":52,"z":4,"images":["oak"]},{"x":3,"y":65,"z":0,"images":["trunk"]},{"x":3,"y":65,"z":4,"images":["brown"]},{"x":0,"y":75,"z":0,"images":["trunk"]},{"x":0,"y":75,"z":4,"images":["oak"]},{"x":0,"y":54,"z":0,"images":["trunk"]},{"x":0,"y":54,"z":4,"images":["pine"]},{"x":4,"y":51,"z":0,"images":["trunk"]},{"x":4,"y":51,"z":4,"images":["oak"]},{"x":5,"y":58,"z":0,"images":["trunk"]},{"x":5,"y":58,"z":4,"images":["oak"]},{"x":0,"y":32,"z":0,"images":["trunk"]},{"x":0,"y":32,"z":4,"images":["pine"]},{"x":9,"y":34,"z":0,"images":["trunk"]},{"x":9,"y":34,"z":4,"images":["oak"]},{"x":6,"y":22,"z":0,"images":["trunk"]},{"x":6,"y":22,"z":4,"images":["oak"]},{"x":32,"y":35,"z":0,"images":["trunk"]},{"x":32,"y":35,"z":4,"images":["oak"]},{"x":36,"y":30,"z":0,"images":["trunk"]},{"x":36,"y":30,"z":4,"images":["oak"]},{"x":39,"y":38,"z":0,"images":["trunk"]},{"x":39,"y":38,"z":4,"images":["brown"]},{"x":36,"y":52,"z":0,"images":["trunk"]},{"x":36,"y":52,"z":4,"images":["oak"]},{"x":47,"y":51,"z":0,"images":["trunk"]},{"x":47,"y":51,"z":4,"images":["brown"]},{"x":19,"y":25,"z":0,"images":["trunk"]},{"x":19,"y":25,"z":4,"images":["oak"]},{"x":28,"y":17,"z":0,"images":["trunk"]},{"x":28,"y":17,"z":4,"images":["brown"]},{"x":32,"y":18,"z":0,"images":["trunk"]},{"x":32,"y":18,"z":4,"images":["oak"]},{"x":14,"y":10,"z":0,"images":["trunk"]},{"x":14,"y":10,"z":4,"images":["oak"]},{"x":2,"y":0,"z":0,"images":["trunk"]},{"x":2,"y":0,"z":4,"images":["oak"]},{"x":13,"y":1,"z":0,"images":["trunk"]},{"x":13,"y":1,"z":4,"images":["brown"]},{"x":23,"y":6,"z":0,"images":["trunk"]},{"x":23,"y":6,"z":4,"images":["pine"]},{"x":29,"y":1,"z":0,"images":["trunk"]},{"x":29,"y":1,"z":4,"images":["brown"]},{"x":33,"y":9,"z":0,"images":["trunk"]},{"x":33,"y":9,"z":4,"images":["oak"]},{"x":44,"y":4,"z":0,"images":["trunk"]},{"x":44,"y":4,"z":4,"images":["pine"]},{"x":48,"y":0,"z":0,"images":["trunk"]},{"x":48,"y":0,"z":4,"images":["brown"]},{"x":54,"y":6,"z":0,"images":["trunk"]},{"x":54,"y":6,"z":4,"images":["oak"]},{"x":61,"y":44,"z":0,"images":["trunk"]},{"x":61,"y":44,"z":4,"images":["oak"]},{"x":70,"y":50,"z":0,"images":["trunk"]},{"x":70,"y":50,"z":4,"images":["oak"]},{"x":74,"y":38,"z":0,"images":["trunk"]},{"x":74,"y":38,"z":4,"images":["oak"]},{"x":70,"y":27,"z":0,"images":["trunk"]},{"x":70,"y":27,"z":4,"images":["pine"]},{"x":61,"y":13,"z":0,"images":["trunk"]},{"x":61,"y":13,"z":4,"images":["pine"]},{"x":69,"y":12,"z":0,"images":["trunk"]},{"x":69,"y":12,"z":4,"images":["oak"]},{"x":64,"y":3,"z":0,"images":["trunk"]},{"x":64,"y":3,"z":4,"images":["pine"]},{"x":81,"y":20,"z":0,"images":["trunk"]},{"x":81,"y":20,"z":4,"images":["oak"]},{"x":82,"y":1,"z":0,"images":["trunk"]},{"x":82,"y":1,"z":4,"images":["brown"]},{"x":90,"y":9,"z":0,"images":["trunk"]},{"x":90,"y":9,"z":4,"images":["oak"]},{"x":96,"y":3,"z":0,"images":["trunk"]},{"x":96,"y":3,"z":4,"images":["oak"]},{"x":95,"y":18,"z":0,"images":["trunk"]},{"x":95,"y":18,"z":4,"images":["oak"]},{"x":94,"y":30,"z":0,"images":["trunk"]},{"x":94,"y":30,"z":4,"images":["oak"]},{"x":92,"y":34,"z":0,"images":["trunk"]},{"x":92,"y":34,"z":4,"images":["pine"]},{"x":82,"y":46,"z":0,"images":["trunk"]},{"x":82,"y":46,"z":4,"images":["oak"]},{"x":87,"y":45,"z":0,"images":["trunk"]},{"x":87,"y":45,"z":4,"images":["brown"]},{"x":91,"y":45,"z":0,"images":["trunk"]},{"x":91,"y":45,"z":4,"images":["brown"]},{"x":91,"y":52,"z":0,"images":["trunk"]},{"x":91,"y":52,"z":4,"images":["oak"]},{"x":93,"y":78,"z":0,"images":["trunk"]},{"x":93,"y":78,"z":4,"images":["oak"]},{"x":98,"y":71,"z":0,"images":["trunk"]},{"x":98,"y":71,"z":4,"images":["pine"]},{"x":76,"y":96,"z":0,"images":["trunk"]},{"x":76,"y":96,"z":4,"images":["pine"]},{"x":80,"y":79,"z":0,"images":["trunk"]},{"x":80,"y":79,"z":4,"images":["pine"]},{"x":44,"y":97,"z":0,"images":["trunk"]},{"x":44,"y":97,"z":4,"images":["oak"]},{"x":54,"y":88,"z":0,"images":["trunk"]},{"x":54,"y":88,"z":4,"images":["pine"]},{"x":62,"y":98,"z":0,"images":["trunk"]},{"x":62,"y":98,"z":4,"images":["pine"]},{"x":55,"y":107,"z":0,"images":["trunk"]},{"x":55,"y":107,"z":4,"images":["oak"]},{"x":60,"y":112,"z":0,"images":["trunk"]},{"x":60,"y":112,"z":4,"images":["oak"]},{"x":71,"y":110,"z":0,"images":["trunk"]},{"x":71,"y":110,"z":4,"images":["oak"]},{"x":59,"y":130,"z":0,"images":["trunk"]},{"x":59,"y":130,"z":4,"images":["pine"]},{"x":62,"y":118,"z":0,"images":["trunk"]},{"x":62,"y":118,"z":4,"images":["brown"]},{"x":52,"y":140,"z":0,"images":["trunk"]},{"x":52,"y":140,"z":4,"images":["brown"]},{"x":58,"y":135,"z":0,"images":["trunk"]},{"x":58,"y":135,"z":4,"images":["pine"]},{"x":76,"y":138,"z":0,"images":["trunk"]},{"x":76,"y":138,"z":4,"images":["oak"]},{"x":79,"y":130,"z":0,"images":["trunk"]},{"x":79,"y":130,"z":4,"images":["oak"]},{"x":38,"y":152,"z":0,"images":["trunk"]},{"x":38,"y":152,"z":4,"images":["oak"]},{"x":43,"y":153,"z":0,"images":["trunk"]},{"x":43,"y":153,"z":4,"images":["brown"]},{"x":46,"y":145,"z":0,"images":["trunk"]},{"x":46,"y":145,"z":4,"images":["oak"]},{"x":66,"y":146,"z":0,"images":["trunk"]},{"x":66,"y":146,"z":4,"images":["oak"]},{"x":94,"y":124,"z":0,"images":["trunk"]},{"x":94,"y":124,"z":4,"images":["oak"]},{"x":96,"y":116,"z":0,"images":["trunk"]},{"x":96,"y":116,"z":4,"images":["pine"]},{"x":91,"y":116,"z":0,"images":["trunk"]},{"x":91,"y":116,"z":4,"images":["pine"]},{"x":98,"y":121,"z":0,"images":["trunk"]},{"x":98,"y":121,"z":4,"images":["oak"]},{"x":91,"y":103,"z":0,"images":["trunk"]},{"x":91,"y":103,"z":4,"images":["pine"]},{"x":49,"y":46,"z":0,"images":["stone.wall.x"]},{"x":54,"y":46,"z":0,"images":["stone.wall.x"]},{"x":50,"y":46,"z":0,"images":["wood.column"]},{"x":45,"y":46,"z":0,"images":["wood.column"]},{"x":55,"y":46,"z":0,"images":["wood.column"]},{"x":55,"y":45,"z":0,"images":["stone.wall.y"]},{"x":45,"y":45,"z":0,"images":["stone.wall.y"]},{"x":45,"y":40,"z":0,"images":["stone.wall.y"]},{"x":55,"y":40,"z":0,"images":["stone.wall.y"]},{"x":45,"y":41,"z":0,"images":["wood.column"]},{"x":55,"y":41,"z":0,"images":["wood.column"]},{"x":55,"y":36,"z":0,"images":["wood.column"]},{"x":45,"y":36,"z":0,"images":["wood.column"]},{"x":54,"y":36,"z":0,"images":["stone.wall.x"]},{"x":50,"y":36,"z":0,"images":["wood.column"]},{"x":46,"y":36,"z":0,"images":["wood.column"]},{"x":48,"y":36,"z":0,"images":["wood.door.x"]},{"x":49,"y":36,"z":0,"images":["wood.column"]}]},{"name":"roof","world":[]}]}